{
    "1A01": {
        "Address": "1450 Spring Place, NW; Washington, DC 20010", 
        "Email": "1A01@anc.dc.gov", 
        "First_Name": "Daniel", 
        "Last_Name": "Kornfield", 
        "Middle_Name": "", 
        "Nickname": "", 
        "Phone": "", 
        "Suffix": ""
    }, 
    "1A02": {
        "Address": "1410 Meridian Place, NW; Washington, DC 20010", 
        "Email": "1A02@anc.dc.gov", 
        "First_Name": "Vickey", 
        "Last_Name": "Wright-Smith", 
        "Middle_Name": "A.", 
        "Nickname": "", 
        "Phone": "", 
        "Suffix": ""
    }, 
    "1A03": {
        "Address": "1440 Columbia Road, NW; Apt. 103; Washington, DC 20009", 
        "Email": "1A03@anc.dc.gov", 
        "First_Name": "Steve", 
        "Last_Name": "Swank", 
        "Middle_Name": "", 
        "Nickname": "", 
        "Phone": "", 
        "Suffix": ""
    }, 
    "1A04": {
        "Address": "3626 13th Street NW; Washington, DC 20010", 
        "Email": "1A04@anc.dc.gov", 
        "First_Name": "Morgan", 
        "Last_Name": "Corr", 
        "Middle_Name": "P.", 
        "Nickname": "", 
        "Phone": "", 
        "Suffix": ""
    }, 
    "1A05": {
        "Address": "1521 Monroe Street, NW; Washington, DC 20010", 
        "Email": "1A05@anc.dc.gov", 
        "First_Name": "Kevin", 
        "Last_Name": "Holmes", 
        "Middle_Name": "", 
        "Nickname": "", 
        "Phone": "", 
        "Suffix": ""
    }, 
    "1A06": {
        "Address": "1364 Kenyon Street, NW; Apt. 1; Washington, DC 20010", 
        "Email": "1A06@anc.dc.gov", 
        "First_Name": "Patrick", 
        "Last_Name": "Flynn", 
        "Middle_Name": "W.", 
        "Nickname": "", 
        "Phone": "", 
        "Suffix": ""
    }, 
    "1A07": {
        "Address": "3516 10th Street, NW; Washington, DC 20010", 
        "Email": "1A07@anc.dc.gov", 
        "First_Name": "Thomas", 
        "Last_Name": "Boisvert", 
        "Middle_Name": "", 
        "Nickname": "", 
        "Phone": "", 
        "Suffix": ""
    }, 
    "1A08": {
        "Address": "608 Rock Creek Church Road, NW;  Washington, DC 20010", 
        "Email": "1A08@anc.dc.gov", 
        "First_Name": "Kent", 
        "Last_Name": "Boese", 
        "Middle_Name": "C.", 
        "Nickname": "", 
        "Phone": "202-904-8111", 
        "Suffix": ""
    }, 
    "1A09": {
        "Address": "641 Keefer Place, NW; Washington, DC 20010", 
        "Email": "1A09@anc.dc.gov", 
        "First_Name": "Bobby", 
        "Last_Name": "Holmes", 
        "Middle_Name": "", 
        "Nickname": "", 
        "Phone": "", 
        "Suffix": ""
    }, 
    "1A10": {
        "Address": "425 Irving Street, NW; Washington, DC 20010", 
        "Email": "1A10@anc.dc.gov", 
        "First_Name": "Anthony", 
        "Last_Name": "Cimino", 
        "Middle_Name": "", 
        "Nickname": "", 
        "Phone": "202-670-2629", 
        "Suffix": ""
    }, 
    "1A11": {
        "Address": "1116 Columbia Road, NW; Washington, DC 20009", 
        "Email": "1A11@anc.dc.gov", 
        "First_Name": "Dotti", 
        "Last_Name": "Wade", 
        "Middle_Name": "Love", 
        "Nickname": "", 
        "Phone": "", 
        "Suffix": ""
    }, 
    "1A12": {
        "Address": "2802 14th Street, NW; Apt. 204; Washington, DC 20009", 
        "Email": "1A12@anc.dc.gov", 
        "First_Name": "Rosalind", 
        "Last_Name": "Gilliam", 
        "Middle_Name": "M.", 
        "Nickname": "", 
        "Phone": "", 
        "Suffix": ""
    }, 
    "1B01": {
        "Address": "1901 4th Street NW Washington, DC 20001", 
        "Email": "1A01@anc.dc.gov", 
        "First_Name": "Marc", 
        "Last_Name": "Morgan", 
        "Middle_Name": "", 
        "Nickname": "", 
        "Phone": "202-280-8935", 
        "Suffix": ""
    }, 
    "1B02": {
        "Address": "2250 11th Street NW Apt 108 Washington, DC 20001", 
        "Email": "1A02@anc.dc.gov", 
        "First_Name": "Jeremy", 
        "Last_Name": "Leffler", 
        "Middle_Name": "C.", 
        "Nickname": "", 
        "Phone": "", 
        "Suffix": ""
    }, 
    "1B03": {
        "Address": "2515 13th Street NW Apt 504 Washington, DC 20009", 
        "Email": "1A03@anc.dc.gov", 
        "First_Name": "Sedrick", 
        "Last_Name": "Mohammad", 
        "Middle_Name": "", 
        "Nickname": "", 
        "Phone": "", 
        "Suffix": ""
    }, 
    "1B04": {
        "Address": "1338 Meridian Place NW Washington, DC 20010", 
        "Email": "1A04@anc.dc.gov", 
        "First_Name": "Deborah", 
        "Last_Name": "Thomas", 
        "Middle_Name": "R.", 
        "Nickname": "", 
        "Phone": "", 
        "Suffix": ""
    }, 
    "1B05": {
        "Address": "1521 Monroe Street NW Washington, DC 20010", 
        "Email": "1A05@anc.dc.gov", 
        "First_Name": "Ricardo", 
        "Last_Name": "Reinoso", 
        "Middle_Name": "A.", 
        "Nickname": "", 
        "Phone": "", 
        "Suffix": ""
    }, 
    "1B06": {
        "Address": "1364 Kenyon Street NW Apt 1 Washington, DC 20010", 
        "Email": "1A06@anc.dc.gov", 
        "First_Name": "Dyana", 
        "Last_Name": "Forester", 
        "Middle_Name": "", 
        "Nickname": "", 
        "Phone": "", 
        "Suffix": ""
    }, 
    "1B07": {
        "Address": "3516 10th Street NW Washington, DC 20010", 
        "Email": "1A07@anc.dc.gov", 
        "First_Name": "Juan", 
        "Last_Name": "Lopez", 
        "Middle_Name": "E.", 
        "Nickname": "", 
        "Phone": "", 
        "Suffix": ""
    }, 
    "1B08": {
        "Address": "608 Rock Creek Church Road NW Washington, DC 20010", 
        "Email": "1A08@anc.dc.gov", 
        "First_Name": "Emily", 
        "Last_Name": "Washington", 
        "Middle_Name": "", 
        "Nickname": "", 
        "Phone": "202-904-8111", 
        "Suffix": ""
    }, 
    "1B09": {
        "Address": "641 Keefer Place NW Washington, DC 20010", 
        "Email": "1A09@anc.dc.gov", 
        "First_Name": "James", 
        "Last_Name": "Turmer", 
        "Middle_Name": "A.", 
        "Nickname": "", 
        "Phone": "", 
        "Suffix": ""
    }, 
    "1B10": {
        "Address": "425 Irving Street NW Washington, DC 20010", 
        "Email": "1A10@anc.dc.gov", 
        "First_Name": "Tony", 
        "Last_Name": "Norman", 
        "Middle_Name": "", 
        "Nickname": "", 
        "Phone": "202-670-2629", 
        "Suffix": ""
    }, 
    "1B11": {
        "Address": "1116 Columbia Road NW Washington, DC 20010", 
        "Email": "1A11@anc.dc.gov", 
        "First_Name": "E.", 
        "Last_Name": "Anderson-Holness", 
        "Middle_Name": "Gail", 
        "Nickname": "", 
        "Phone": "", 
        "Suffix": ""
    }, 
    "1B12": {
        "Address": "2802 14th Street NW Apt 204 Washington, DC 20010", 
        "Email": "1A12@anc.dc.gov", 
        "First_Name": "Zahra", 
        "Last_Name": "Jilani", 
        "Middle_Name": "", 
        "Nickname": "", 
        "Phone": "", 
        "Suffix": ""
    }, 
    "1C01": {
        "Address": "1850 Wyoming Avenue, NW; Apt. 1; Washington, DC 20009", 
        "Email": "1C01@anc.dc.gov", 
        "First_Name": "Brian", 
        "Last_Name": "Hart", 
        "Middle_Name": "", 
        "Nickname": "", 
        "Phone": "202-223-7349", 
        "Suffix": ""
    }, 
    "1C02": {
        "Address": "2032 Belmont Road, NW; Apt. 607; Washington, DC 20009", 
        "Email": "1C02@anc.dc.gov", 
        "First_Name": "Martis", 
        "Last_Name": "Davis", 
        "Middle_Name": "Marty", 
        "Nickname": "", 
        "Phone": "202-328-3817", 
        "Suffix": ""
    }, 
    "1C03": {
        "Address": "1849 Kalorama Road, NW; Apt. 2; Washington, DC 20009", 
        "Email": "1C03@anc.dc.gov", 
        "First_Name": "Ted", 
        "Last_Name": "Guthrie", 
        "Middle_Name": "", 
        "Nickname": "", 
        "Phone": "", 
        "Suffix": ""
    }, 
    "1C04": {
        "Address": "2853 Ontario Road, NW; Washington, DC 20009", 
        "Email": "1C04@anc.dc.gov", 
        "First_Name": "Gabriela", 
        "Last_Name": "Mossi", 
        "Middle_Name": "", 
        "Nickname": "", 
        "Phone": "", 
        "Suffix": ""
    }, 
    "1C05": {
        "Address": "1731 Lanier Place, NW; Washington, DC 20009", 
        "Email": "1C05@anc.dc.gov", 
        "First_Name": "Elham", 
        "Last_Name": "Dehbozorgi", 
        "Middle_Name": "", 
        "Nickname": "", 
        "Phone": "202-658-8161", 
        "Suffix": ""
    }, 
    "1C06": {
        "Address": "1721 Euclid Street, NW; Washington, DC 20009", 
        "Email": "1C06@anc.dc.gov", 
        "First_Name": "William", 
        "Last_Name": "Simpson", 
        "Middle_Name": "", 
        "Nickname": "", 
        "Phone": "", 
        "Suffix": ""
    }, 
    "1C07": {
        "Address": "2370 Champlain Street, NW; Apt. 23; Washington, DC 20009", 
        "Email": "1C07@anc.dc.gov", 
        "First_Name": "Wilson", 
        "Last_Name": "Reynolds", 
        "Middle_Name": "", 
        "Nickname": "", 
        "Phone": "986-2213 x4", 
        "Suffix": ""
    }, 
    "1C08": {
        "Address": "2440 16th Street, NW; Apt. 106; Washington, DC 20009", 
        "Email": "1C08@anc.dc.gov", 
        "First_Name": "Jimmy", 
        "Last_Name": "Rock", 
        "Middle_Name": "R.", 
        "Nickname": "", 
        "Phone": "", 
        "Suffix": ""
    }, 
    "1D01": {
        "Address": "3354 Mt. Pleasant Street NW Apt. 9; Washington, DC 20010", 
        "Email": "1D01@anc.dc.gov", 
        "First_Name": "Yasmin", 
        "Last_Name": "Romero-Castillo", 
        "Middle_Name": "", 
        "Nickname": "", 
        "Phone": "202-486-6677", 
        "Suffix": ""
    }, 
    "1D02": {
        "Address": "1655 Newton Street NW; Washington, DC 20010", 
        "Email": "1D02@anc.dc.gov", 
        "First_Name": "Adam", 
        "Last_Name": "Hoey", 
        "Middle_Name": "", 
        "Nickname": "", 
        "Phone": "", 
        "Suffix": ""
    }, 
    "1D03": {
        "Address": "3200 19th Street NW; Washington, DC 20010", 
        "Email": "1D03@anc.dc.gov", 
        "First_Name": "Jack", 
        "Last_Name": "McKay", 
        "Middle_Name": "", 
        "Nickname": "", 
        "Phone": "202-462-8692", 
        "Suffix": ""
    }, 
    "1D04": {
        "Address": "1665 Lamont Street NW Apt. 31; Washington, DC 20010", 
        "Email": "1D04@anc.dc.gov", 
        "First_Name": "Phil", 
        "Last_Name": "Greiner", 
        "Middle_Name": "", 
        "Nickname": "", 
        "Phone": "", 
        "Suffix": ""
    }, 
    "1D05": {
        "Address": "1900 Lamont Street NW Apt. 304; Washington, DC 20010", 
        "Email": "1D05@anc.dc.gov", 
        "First_Name": "China", 
        "Last_Name": "Terrell", 
        "Middle_Name": "", 
        "Nickname": "", 
        "Phone": "202-550-1707", 
        "Suffix": ""
    }, 
    "2A01": {
        "Address": "2020 F Street NW #530; Washington, DC 20006", 
        "Email": "2A01@anc.dc.gov", 
        "First_Name": "Patrick", 
        "Last_Name": "Kennedy", 
        "Middle_Name": "", 
        "Nickname": "", 
        "Phone": "202-630-2201", 
        "Suffix": ""
    }, 
    "2A02": {
        "Address": "2501 M Street NW #721; Washington, DC 20037", 
        "Email": "2A02@anc.dc.gov", 
        "First_Name": "Rebecca", 
        "Last_Name": "Coder", 
        "Middle_Name": "", 
        "Nickname": "", 
        "Phone": "202-955-8333", 
        "Suffix": ""
    }, 
    "2A03": {
        "Address": "955 26th Street NW #709; Washington, DC 20037", 
        "Email": "2A03@anc.dc.gov", 
        "First_Name": "Asher", 
        "Last_Name": "Corson", 
        "Middle_Name": "", 
        "Nickname": "", 
        "Phone": "202-741-0932", 
        "Suffix": ""
    }, 
    "2A04": {
        "Address": "2475 Virginia Avenue NW #911; Washington, DC 20037", 
        "Email": "2A04@anc.dc.gov", 
        "First_Name": "Armando", 
        "Last_Name": "Irizarry", 
        "Middle_Name": "", 
        "Nickname": "", 
        "Phone": "", 
        "Suffix": ""
    }, 
    "2A05": {
        "Address": "2450 Virginia Avenue NW #E319; Washington, DC 20037", 
        "Email": "2A05@anc.dc.gov", 
        "First_Name": "Graham", 
        "Last_Name": "Galka", 
        "Middle_Name": "M.", 
        "Nickname": "", 
        "Phone": "", 
        "Suffix": ""
    }, 
    "2A06": {
        "Address": "1099 22nd Street NW #1011; Washington, DC 20037", 
        "Email": "2A06@anc.dc.gov", 
        "First_Name": "Florence", 
        "Last_Name": "Harmon", 
        "Middle_Name": "E.", 
        "Nickname": "", 
        "Phone": "202-390-4438", 
        "Suffix": ""
    }, 
    "2A07": {
        "Address": "510 21st Street NW #405; Washington, DC 20006", 
        "Email": "2A07@anc.dc.gov", 
        "First_Name": "Jackson", 
        "Last_Name": "Carnes", 
        "Middle_Name": "", 
        "Nickname": "", 
        "Phone": "", 
        "Suffix": ""
    }, 
    "2A08": {
        "Address": "600 20th Street NW #712 ; Washington, DC 20052", 
        "Email": "2A08@anc.dc.gov", 
        "First_Name": "Peter", 
        "Last_Name": "Sacco", 
        "Middle_Name": "E.", 
        "Nickname": "", 
        "Phone": "978-882-5013", 
        "Suffix": ""
    }, 
    "2B01": {
        "Address": "1920 S Street, NW; Apt. 203; Washington, DC 20009", 
        "Email": "2B01@anc.dc.gov", 
        "First_Name": "Michael", 
        "Last_Name": "Feldstein", 
        "Middle_Name": "", 
        "Nickname": "", 
        "Phone": "202-462-0647", 
        "Suffix": ""
    }, 
    "2B02": {
        "Address": "2147 O Street, NW; Apt. 309; Washington, DC 20037", 
        "Email": "2B02@anc.dc.gov", 
        "First_Name": "Kevin", 
        "Last_Name": "O'Connor", 
        "Middle_Name": "", 
        "Nickname": "", 
        "Phone": "", 
        "Suffix": ""
    }, 
    "2B03": {
        "Address": "1727 R Street, NW; Apt. 402; Washington, DC 20009", 
        "Email": "2B03@anc.dc.gov", 
        "First_Name": "Stephanie", 
        "Last_Name": "Maltz", 
        "Middle_Name": "", 
        "Nickname": "", 
        "Phone": "202-630-7262", 
        "Suffix": ""
    }, 
    "2B04": {
        "Address": "1701 16th Street, NW; Apt. 701; Washington, DC 20009", 
        "Email": "2B04@anc.dc.gov", 
        "First_Name": "Kishan", 
        "Last_Name": "Putta", 
        "Middle_Name": "", 
        "Nickname": "", 
        "Phone": "", 
        "Suffix": ""
    }, 
    "2B05": {
        "Address": "1325 18th Street NW; Apt. 803; Washington, DC 20036", 
        "Email": "2B05@anc.dc.gov", 
        "First_Name": "Abigail", 
        "Last_Name": "Nichols", 
        "Middle_Name": "C.", 
        "Nickname": "", 
        "Phone": "", 
        "Suffix": ""
    }, 
    "2B06": {
        "Address": "1301 20th Street, NW; Apt. 705; Washington, DC 20036", 
        "Email": "2B06@anc.dc.gov", 
        "First_Name": "Mike", 
        "Last_Name": "Silverstein", 
        "Middle_Name": "", 
        "Nickname": "", 
        "Phone": "202-833-4440", 
        "Suffix": ""
    }, 
    "2B07": {
        "Address": "1514 17th Street, NW; Apt. 501; Washington, DC 20036", 
        "Email": "2B07@anc.dc.gov", 
        "First_Name": "Leo", 
        "Last_Name": "Dwyer", 
        "Middle_Name": "", 
        "Nickname": "", 
        "Phone": "", 
        "Suffix": ""
    }, 
    "2B08": {
        "Address": "9 Dupont Circle, NW; Washington, DC 20036", 
        "Email": "2B08@anc.dc.gov", 
        "First_Name": "Will", 
        "Last_Name": "Stephens", 
        "Middle_Name": "", 
        "Nickname": "", 
        "Phone": "202-657-4157", 
        "Suffix": ""
    }, 
    "2B09": {
        "Address": "1815 17th Street, NW; Apt. 412; Washington, DC 20009", 
        "Email": "2B09@anc.dc.gov", 
        "First_Name": "Noah", 
        "Last_Name": "Smith", 
        "Middle_Name": "", 
        "Nickname": "", 
        "Phone": "", 
        "Suffix": ""
    }, 
    "2C01": {
        "Address": "777 7th Street, NW; Apt. 506; Washington, DC 20001", 
        "Email": "2C01@anc.dc.gov", 
        "First_Name": "John", 
        "Last_Name": "Tinpe", 
        "Middle_Name": "", 
        "Nickname": "", 
        "Phone": "202-230-8538", 
        "Suffix": ""
    }, 
    "2C02": {
        "Address": "400 Massachusetts Avenue, NW; Apt. 1019; Washington, DC 20001", 
        "Email": "2C02@anc.dc.gov", 
        "First_Name": "Harold", 
        "Last_Name": "Closter", 
        "Middle_Name": "", 
        "Nickname": "", 
        "Phone": "", 
        "Suffix": ""
    }, 
    "2C03": {
        "Address": "425 8th Street, NW; Apt. 845; Washington, DC 20004", 
        "Email": "2C03@anc.dc.gov", 
        "First_Name": "Kevin", 
        "Last_Name": "Wilsey", 
        "Middle_Name": "", 
        "Nickname": "", 
        "Phone": "202-393-2310", 
        "Suffix": ""
    }, 
    "2D01": {
        "Address": "2126 Connecticut Avenue, NW; Apt. 34; Washington, DC 20008", 
        "Email": "2D01@anc.dc.gov", 
        "First_Name": "David", 
        "Last_Name": "Bender", 
        "Middle_Name": "R.", 
        "Nickname": "", 
        "Phone": "202-483-0839", 
        "Suffix": ""
    }, 
    "2D02": {
        "Address": "2122 California Street, NW; Apt. 62; Washington, DC 20008", 
        "Email": "2D02@anc.dc.gov", 
        "First_Name": "Eric", 
        "Last_Name": "Lamar", 
        "Middle_Name": "", 
        "Nickname": "", 
        "Phone": "", 
        "Suffix": ""
    }, 
    "2E01": {
        "Address": "3525 S Street, NW; Washington, DC 20007", 
        "Email": "2E01@anc.dc.gov", 
        "First_Name": "Ed", 
        "Last_Name": "Soloman", 
        "Middle_Name": "", 
        "Nickname": "", 
        "Phone": "", 
        "Suffix": ""
    }, 
    "2E02": {
        "Address": "3400 Reservoir Road, NW; Washington, DC 20007", 
        "Email": "2E02@anc.dc.gov", 
        "First_Name": "Ron", 
        "Last_Name": "Lewis", 
        "Middle_Name": "", 
        "Nickname": "", 
        "Phone": "", 
        "Suffix": ""
    }, 
    "2E03": {
        "Address": "3526 P Street, NW; Washington, DC 20007", 
        "Email": "2E03@anc.dc.gov", 
        "First_Name": "Jeffrey", 
        "Last_Name": "Jones", 
        "Middle_Name": "", 
        "Nickname": "", 
        "Phone": "", 
        "Suffix": ""
    }, 
    "2E04": {
        "Address": "Village C West 545 Georgetown University; Washington, DC 20057", 
        "Email": "2E04@anc.dc.gov", 
        "First_Name": "Craig", 
        "Last_Name": "Cassey,", 
        "Middle_Name": "", 
        "Nickname": "", 
        "Phone": "", 
        "Suffix": "Jr."
    }, 
    "2E05": {
        "Address": "1045 31st Street NW  Apt. 502; Washington, DC 20007", 
        "Email": "2E05@anc.dc.gov", 
        "First_Name": "Bill", 
        "Last_Name": "Starrels", 
        "Middle_Name": "", 
        "Nickname": "", 
        "Phone": "202-338-1450", 
        "Suffix": ""
    }, 
    "2E06": {
        "Address": "1240 29th Street, NW; Washington, DC 20007", 
        "Email": "2E06@anc.dc.gov", 
        "First_Name": "Tom", 
        "Last_Name": "Birch", 
        "Middle_Name": "", 
        "Nickname": "", 
        "Phone": "202-342-6262", 
        "Suffix": ""
    }, 
    "2E07": {
        "Address": "2800 R Street NW; Washington, DC 20007", 
        "Email": "2E07@anc.dc.gov", 
        "First_Name": "Ellen", 
        "Last_Name": "Steury", 
        "Middle_Name": "", 
        "Nickname": "", 
        "Phone": "202-406-0835", 
        "Suffix": ""
    }, 
    "2E08": {
        "Address": "3629 Prospect Street, NW; Washington, DC 20007", 
        "Email": "2E08@anc.dc.gov", 
        "First_Name": "Peter", 
        "Last_Name": "Prindiville", 
        "Middle_Name": "", 
        "Nickname": "", 
        "Phone": "202-643-8293", 
        "Suffix": ""
    }, 
    "2F01": {
        "Address": "1315 Riggs Street, NW; Apt. 3; Washington, DC 20009", 
        "Email": "2F01@anc.dc.gov", 
        "First_Name": "Peter", 
        "Last_Name": "Lallas", 
        "Middle_Name": "", 
        "Nickname": "", 
        "Phone": "", 
        "Suffix": ""
    }, 
    "2F02": {
        "Address": "1325 15th Street, NW; Apt. 1004; Washington, DC 20005", 
        "Email": "2F02@anc.dc.gov", 
        "First_Name": "Walt", 
        "Last_Name": "Cain", 
        "Middle_Name": "", 
        "Nickname": "", 
        "Phone": "601-941-9869", 
        "Suffix": ""
    }, 
    "2F03": {
        "Address": "1301 15th Street, NW; Apt. 620; Washington, DC 20005", 
        "Email": "2F03@anc.dc.gov", 
        "First_Name": "Chris", 
        "Last_Name": "Linn", 
        "Middle_Name": "", 
        "Nickname": "", 
        "Phone": "", 
        "Suffix": ""
    }, 
    "2F04": {
        "Address": "1307 12th Street, NW; Apt. 505; Washington, DC 20005", 
        "Email": "2F04@anc.dc.gov", 
        "First_Name": "John", 
        "Last_Name": "Fanning", 
        "Middle_Name": "", 
        "Nickname": "", 
        "Phone": "202-510-1983", 
        "Suffix": ""
    }, 
    "2F05": {
        "Address": "1330 Massachusetts Avenue, NW; Apt. 605; Washington, DC 20005", 
        "Email": "2F05@anc.dc.gov", 
        "First_Name": "Jim", 
        "Last_Name": "Lamare", 
        "Middle_Name": "", 
        "Nickname": "", 
        "Phone": "", 
        "Suffix": ""
    }, 
    "2F06": {
        "Address": "1327 10th Street, NW; Washington, DC 20001", 
        "Email": "2F06@anc.dc.gov", 
        "First_Name": "Greg", 
        "Last_Name": "Melcher", 
        "Middle_Name": "", 
        "Nickname": "", 
        "Phone": "", 
        "Suffix": ""
    }, 
    "2F07": {
        "Address": "1209 13th Street, NW; Apt. 804; Washington, DC 20005", 
        "Email": "2F07@anc.dc.gov", 
        "First_Name": "Matt", 
        "Last_Name": "Raymond", 
        "Middle_Name": "", 
        "Nickname": "", 
        "Phone": "", 
        "Suffix": ""
    }, 
    "2F08": {
        "Address": "1212 M Street, NW; Apt. 101; Washington, DC 20005", 
        "Email": "2F08@anc.dc.gov", 
        "First_Name": "Matthew", 
        "Last_Name": "Connolly", 
        "Middle_Name": "", 
        "Nickname": "", 
        "Phone": "", 
        "Suffix": ""
    }, 
    "3B01": {
        "Address": "3851 Calvert Street, NW; Washington, DC 20007", 
        "Email": "3B01@anc.dc.gov", 
        "First_Name": "Joe", 
        "Last_Name": "Fiorillo", 
        "Middle_Name": "", 
        "Nickname": "", 
        "Phone": "", 
        "Suffix": ""
    }, 
    "3B02": {
        "Address": "3515 W Place, NW; Washington, DC 20007", 
        "Email": "3B02@anc.dc.gov", 
        "First_Name": "Jackie", 
        "Last_Name": "Blumenthal", 
        "Middle_Name": "", 
        "Nickname": "", 
        "Phone": "", 
        "Suffix": ""
    }, 
    "3B03": {
        "Address": "2325 42nd Street, NW  Apt. 221; Washington, DC 20007", 
        "Email": "3B03@anc.dc.gov", 
        "First_Name": "Charles", 
        "Last_Name": "Fulwood", 
        "Middle_Name": "Cinque", 
        "Nickname": "", 
        "Phone": "202-338-9484", 
        "Suffix": ""
    }, 
    "3B04": {
        "Address": "3040 Idaho Avenue, NW  Apt. 722; Washington, DC 20016", 
        "Email": "3B04@anc.dc.gov", 
        "First_Name": "Mary", 
        "Last_Name": "Young", 
        "Middle_Name": "C.", 
        "Nickname": "", 
        "Phone": "202-895-0268", 
        "Suffix": ""
    }, 
    "3B05": {
        "Address": "3908 Benton Street, NW; Washington, DC 20007", 
        "Email": "3B05@anc.dc.gov", 
        "First_Name": "Brian", 
        "Last_Name": "Cohen", 
        "Middle_Name": "A.", 
        "Nickname": "", 
        "Phone": "", 
        "Suffix": ""
    }, 
    "3C01": {
        "Address": "2829 Connecticut Avenue, NW; Washington, DC 20008", 
        "Email": "3C01@anc.dc.gov", 
        "First_Name": "Lee", 
        "Last_Name": "Reba", 
        "Middle_Name": "Brian", 
        "Nickname": "", 
        "Phone": "202-328-2212", 
        "Suffix": ""
    }, 
    "3C02": {
        "Address": "2833 29th Place, NW; Washington, DC 20008", 
        "Email": "3C02@anc.dc.gov", 
        "First_Name": "Gwendolyn", 
        "Last_Name": "Bole", 
        "Middle_Name": "", 
        "Nickname": "", 
        "Phone": "", 
        "Suffix": ""
    }, 
    "3C03": {
        "Address": "2813 27th Street, NW; Washington, DC 20008", 
        "Email": "3C03@anc.dc.gov", 
        "First_Name": "Jeffrey", 
        "Last_Name": "Kaliel", 
        "Middle_Name": "", 
        "Nickname": "", 
        "Phone": "202-615-3948", 
        "Suffix": ""
    }, 
    "3C04": {
        "Address": "2720 Ordway Street, NW; Apt. 6; Washington, DC 20008", 
        "Email": "3C04@anc.dc.gov", 
        "First_Name": "Richard", 
        "Last_Name": "Steacy", 
        "Middle_Name": "", 
        "Nickname": "", 
        "Phone": "", 
        "Suffix": ""
    }, 
    "3C05": {
        "Address": "3019 Ordway Street, NW; Washington, DC 20008", 
        "Email": "3C05@anc.dc.gov", 
        "First_Name": "Margaret", 
        "Last_Name": "Siegel", 
        "Middle_Name": "A.", 
        "Nickname": "", 
        "Phone": "", 
        "Suffix": ""
    }, 
    "3C06": {
        "Address": "3530 39th Street, NW; Apt. A649; Washington, DC 20016", 
        "Email": "3C06@anc.dc.gov", 
        "First_Name": "Carl", 
        "Last_Name": "Roller", 
        "Middle_Name": "", 
        "Nickname": "", 
        "Phone": "202-505-3206", 
        "Suffix": ""
    }, 
    "3C07": {
        "Address": "3810 Klingle Place, NW; Washington, DC 20016", 
        "Email": "3C07@anc.dc.gov", 
        "First_Name": "Victor", 
        "Last_Name": "Silveira", 
        "Middle_Name": "", 
        "Nickname": "", 
        "Phone": "202-684-6635", 
        "Suffix": ""
    }, 
    "3C08": {
        "Address": "2800 36th Street, NW; Washington, DC 20007", 
        "Email": "3C08@anc.dc.gov", 
        "First_Name": "Catherine", 
        "Last_Name": "May", 
        "Middle_Name": "", 
        "Nickname": "", 
        "Phone": "202-466-3455", 
        "Suffix": ""
    }, 
    "3C09": {
        "Address": "3417 Woodley Road, NW; Washington, DC 20016", 
        "Email": "3C09@anc.dc.gov", 
        "First_Name": "Nancy", 
        "Last_Name": "MacWood", 
        "Middle_Name": "J.", 
        "Nickname": "", 
        "Phone": "202-966-5333", 
        "Suffix": ""
    }, 
    "3D01": {
        "Address": "4505 Dexter Street NW; Washington, DC 20016", 
        "Email": "3D01@anc.dc.gov", 
        "First_Name": "W.", 
        "Last_Name": "Slowinski", 
        "Middle_Name": "Kent", 
        "Nickname": "", 
        "Phone": "", 
        "Suffix": ""
    }, 
    "3D02": {
        "Address": "4601 Tilden Street NW; Washington, DC 20016", 
        "Email": "3D02@anc.dc.gov", 
        "First_Name": "Thomas", 
        "Last_Name": "Smith", 
        "Middle_Name": "M.", 
        "Nickname": "", 
        "Phone": "", 
        "Suffix": ""
    }, 
    "3D03": {
        "Address": "5057 Overlook Road NW; Washington, DC 20016", 
        "Email": "3D03@anc.dc.gov", 
        "First_Name": "Nan", 
        "Last_Name": "Wells", 
        "Middle_Name": "S.", 
        "Nickname": "", 
        "Phone": "202-362-4088", 
        "Suffix": ""
    }, 
    "3D04": {
        "Address": "5445 Potomac Avenue NW; Washington, DC 20016", 
        "Email": "3D04@anc.dc.gov", 
        "First_Name": "Stuart", 
        "Last_Name": "Ross", 
        "Middle_Name": "", 
        "Nickname": "", 
        "Phone": "", 
        "Suffix": ""
    }, 
    "3D05": {
        "Address": "2830 University Terrace NW; Washington, DC 20016", 
        "Email": "3D05@anc.dc.gov", 
        "First_Name": "W.", 
        "Last_Name": "Thomas", 
        "Middle_Name": "Philip", 
        "Nickname": "", 
        "Phone": "", 
        "Suffix": ""
    }, 
    "3D06": {
        "Address": "4701 Berkeley Terrace NW; Washington, DC 20007", 
        "Email": "3D06@anc.dc.gov", 
        "First_Name": "Penny", 
        "Last_Name": "Pagano", 
        "Middle_Name": "", 
        "Nickname": "", 
        "Phone": "202-338-7926", 
        "Suffix": ""
    }, 
    "3D07": {
        "Address": "Cassell Hall 506B; 4400 Massachusetts Avenue NW  ; Washington, DC 20016", 
        "Email": "3D07@anc.dc.gov", 
        "First_Name": "Rory", 
        "Last_Name": "Slatko", 
        "Middle_Name": "", 
        "Nickname": "", 
        "Phone": "", 
        "Suffix": ""
    }, 
    "3D08": {
        "Address": "3101 New Mexico Avenue NW Apt. 243; Washington, DC 20016", 
        "Email": "3D08@anc.dc.gov", 
        "First_Name": "Mike", 
        "Last_Name": "Gold", 
        "Middle_Name": "", 
        "Nickname": "", 
        "Phone": "", 
        "Suffix": ""
    }, 
    "3D09": {
        "Address": "1935 Foxview Circle NW; Washington, DC 20007", 
        "Email": "3D09@anc.dc.gov", 
        "First_Name": "Gayle", 
        "Last_Name": "Trotter", 
        "Middle_Name": "", 
        "Nickname": "", 
        "Phone": "", 
        "Suffix": ""
    }, 
    "3D10": {
        "Address": "4201 Massachusetts Avenue NW Apt. 4041C; Washington, DC 20016", 
        "Email": "3D10@anc.dc.gov", 
        "First_Name": "Joe", 
        "Last_Name": "Wisniewski", 
        "Middle_Name": "", 
        "Nickname": "", 
        "Phone": "202-707-0554", 
        "Suffix": ""
    }, 
    "3E01": {
        "Address": "4101 Albenarle Street NW; Washington, DC 20016", 
        "Email": "3E01@anc.dc.gov", 
        "First_Name": "Kathryn", 
        "Last_Name": "Tinker", 
        "Middle_Name": "", 
        "Nickname": "", 
        "Phone": "", 
        "Suffix": ""
    }, 
    "3E02": {
        "Address": "4709 Albemarle Street NW; Washington, DC 20016", 
        "Email": "3E02@anc.dc.gov", 
        "First_Name": "Matthew", 
        "Last_Name": "Frumin", 
        "Middle_Name": "", 
        "Nickname": "", 
        "Phone": "202-249-0819", 
        "Suffix": ""
    }, 
    "3E03": {
        "Address": "4411 Fessenden Street NW; Washington, DC 20016", 
        "Email": "3E03@anc.dc.gov", 
        "First_Name": "Jonathan", 
        "Last_Name": "Bender", 
        "Middle_Name": "", 
        "Nickname": "", 
        "Phone": "202-552-1420", 
        "Suffix": ""
    }, 
    "3E04": {
        "Address": "5322 41st Street NW; Washington, DC 20015", 
        "Email": "3E04@anc.dc.gov", 
        "First_Name": "Tom", 
        "Last_Name": "Quinn", 
        "Middle_Name": "", 
        "Nickname": "", 
        "Phone": "202-497-5097", 
        "Suffix": ""
    }, 
    "3E05": {
        "Address": "4300 Van Ness Street NW; Washington, DC 20016", 
        "Email": "3E05@anc.dc.gov", 
        "First_Name": "Sam", 
        "Last_Name": "Serebin", 
        "Middle_Name": "", 
        "Nickname": "", 
        "Phone": "", 
        "Suffix": ""
    }, 
    "3F01": {
        "Address": "4319 Reno Road, NW; Washington, DC 20008", 
        "Email": "3F01@anc.dc.gov", 
        "First_Name": "Adam", 
        "Last_Name": "Tope", 
        "Middle_Name": "", 
        "Nickname": "", 
        "Phone": "202-842-4843", 
        "Suffix": ""
    }, 
    "3F02": {
        "Address": "3003 Van Ness Street, NW  Apt. W-118; Washington, DC 20008", 
        "Email": "3F02@anc.dc.gov", 
        "First_Name": "Karen", 
        "Last_Name": "Perry", 
        "Middle_Name": "Lee", 
        "Nickname": "", 
        "Phone": "", 
        "Suffix": ""
    }, 
    "3F03": {
        "Address": "4526 29th Street, NW; Washington, DC 20008", 
        "Email": "3F03@anc.dc.gov", 
        "First_Name": "Mary", 
        "Last_Name": "Ray", 
        "Middle_Name": "Beth", 
        "Nickname": "", 
        "Phone": "", 
        "Suffix": ""
    }, 
    "3F04": {
        "Address": "3222 Davenport Street NW; Washington, DC 20008", 
        "Email": "3F04@anc.dc.gov", 
        "First_Name": "Sally", 
        "Last_Name": "Gresham", 
        "Middle_Name": "W.", 
        "Nickname": "", 
        "Phone": "", 
        "Suffix": ""
    }, 
    "3F05": {
        "Address": "5201 Nebraska Avenue, NW; Washington, DC 20015", 
        "Email": "3F05@anc.dc.gov", 
        "First_Name": "Manolis", 
        "Last_Name": "Priniotakis", 
        "Middle_Name": "R.", 
        "Nickname": "", 
        "Phone": "202-746-6943", 
        "Suffix": ""
    }, 
    "3F06": {
        "Address": "4521 36th Street, NW; Washington, DC 20008", 
        "Email": "3F06@anc.dc.gov", 
        "First_Name": "David", 
        "Last_Name": "Lowell", 
        "Middle_Name": "Solorzano", 
        "Nickname": "", 
        "Phone": "", 
        "Suffix": ""
    }, 
    "3F07": {
        "Address": "3701 Connecticut Avenue, NW  Apt. 139; Washington, DC 20008", 
        "Email": "3F07@anc.dc.gov", 
        "First_Name": "Bob", 
        "Last_Name": "Summersgill", 
        "Middle_Name": "", 
        "Nickname": "", 
        "Phone": "202-341-0457", 
        "Suffix": ""
    }, 
    "3G01": {
        "Address": "6521 Barnaby Street, NW; Washington, DC 20015", 
        "Email": "3G01@anc.dc.gov", 
        "First_Name": "Carolyn", 
        "Last_Name": "Cook", 
        "Middle_Name": "A.", 
        "Nickname": "", 
        "Phone": "", 
        "Suffix": ""
    }, 
    "3G02": {
        "Address": "2840 Northampton Street, NW; Washington, DC 20015", 
        "Email": "3G02@anc.dc.gov", 
        "First_Name": "Gary", 
        "Last_Name": "Thompson", 
        "Middle_Name": "", 
        "Nickname": "", 
        "Phone": "202-256-9910", 
        "Suffix": ""
    }, 
    "3G03": {
        "Address": "2940 Northampton Street, NW; Washington, DC 20015", 
        "Email": "3G03@anc.dc.gov", 
        "First_Name": "Randy", 
        "Last_Name": "Speck", 
        "Middle_Name": "", 
        "Nickname": "", 
        "Phone": "202-244-2620", 
        "Suffix": ""
    }, 
    "3G04": {
        "Address": "P.O. Box 6252; Washington, DC 20015", 
        "Email": "3G04@anc.dc.gov", 
        "First_Name": "Rebecca", 
        "Last_Name": "Maydak", 
        "Middle_Name": "", 
        "Nickname": "", 
        "Phone": "202-321-7871", 
        "Suffix": ""
    }, 
    "3G05": {
        "Address": "3731 Northampton Street, NW; Washington, DC 20015", 
        "Email": "3G05@anc.dc.gov", 
        "First_Name": "David", 
        "Last_Name": "Engel", 
        "Middle_Name": "", 
        "Nickname": "", 
        "Phone": "", 
        "Suffix": ""
    }, 
    "3G06": {
        "Address": "3835 Livingston Street, NW; Washington, DC 20015", 
        "Email": "3G06@anc.dc.gov", 
        "First_Name": "Jim", 
        "Last_Name": "McCarthy", 
        "Middle_Name": "", 
        "Nickname": "", 
        "Phone": "", 
        "Suffix": ""
    }, 
    "3G07": {
        "Address": "3729 Joycelyn Street, NW; Washington, DC 20015", 
        "Email": "3G07@anc.dc.gov", 
        "First_Name": "Henry", 
        "Last_Name": "Griffin", 
        "Middle_Name": "", 
        "Nickname": "", 
        "Phone": "", 
        "Suffix": ""
    }, 
    "4A01": {
        "Address": "7247 15th Place NW; Washington, DC 20012", 
        "Email": "4A01@anc.dc.gov", 
        "First_Name": "Acqunetta", 
        "Last_Name": "Anderson", 
        "Middle_Name": "", 
        "Nickname": "", 
        "Phone": "", 
        "Suffix": ""
    }, 
    "4A02": {
        "Address": "1326 Hemlock Street NW; Washington, DC 20012", 
        "Email": "4A02@anc.dc.gov", 
        "First_Name": "Dwayne", 
        "Last_Name": "Toliver", 
        "Middle_Name": "M.", 
        "Nickname": "", 
        "Phone": "202-360-3334", 
        "Suffix": ""
    }, 
    "4A03": {
        "Address": "1315 Fern Street NW; Washington, DC 20012", 
        "Email": "4A03@anc.dc.gov", 
        "First_Name": "Stephen", 
        "Last_Name": "Whatley", 
        "Middle_Name": "A.", 
        "Nickname": "", 
        "Phone": "202-720-4590", 
        "Suffix": ""
    }, 
    "4A04": {
        "Address": "Washington, DC 20011", 
        "Email": "4A04@anc.dc.gov", 
        "First_Name": "Vacant", 
        "Last_Name": "Vacant", 
        "Middle_Name": "", 
        "Nickname": "", 
        "Phone": "", 
        "Suffix": ""
    }, 
    "4A05": {
        "Address": "6101 16th Street NW  APT 905; Washington, DC 20011", 
        "Email": "4A05@anc.dc.gov", 
        "First_Name": "Martha", 
        "Last_Name": "Mitchell", 
        "Middle_Name": "", 
        "Nickname": "", 
        "Phone": "", 
        "Suffix": ""
    }, 
    "4A06": {
        "Address": "1320 Missouri Avenue NW APT 102; Washington, DC 20011", 
        "Email": "4A06@anc.dc.gov", 
        "First_Name": "Karrye", 
        "Last_Name": "Braxton", 
        "Middle_Name": "Y.", 
        "Nickname": "", 
        "Phone": "", 
        "Suffix": ""
    }, 
    "4A07": {
        "Address": "5810 16th Street, NW; Washington, DC 20011", 
        "Email": "4A07@anc.dc.gov", 
        "First_Name": "Dave", 
        "Last_Name": "Wilson", 
        "Middle_Name": "", 
        "Nickname": "", 
        "Phone": "202-441-7888", 
        "Suffix": ""
    }, 
    "4A08": {
        "Address": "1761 Crestwood Drive, NW; Washington, DC 20011", 
        "Email": "4A08@anc.dc.gov", 
        "First_Name": "Gale", 
        "Last_Name": "Black", 
        "Middle_Name": "B.", 
        "Nickname": "", 
        "Phone": "", 
        "Suffix": ""
    }, 
    "4B01": {
        "Address": "7106 Piney Branch Road, NW; Washington, DC 20012", 
        "Email": "4B01@anc.dc.gov", 
        "First_Name": "Sara", 
        "Last_Name": "Green", 
        "Middle_Name": "", 
        "Nickname": "", 
        "Phone": "202-829-8802", 
        "Suffix": ""
    }, 
    "4B02": {
        "Address": "818 Whittier Place, NW; Washington, DC 20012", 
        "Email": "4B02@anc.dc.gov", 
        "First_Name": "Faith", 
        "Last_Name": "Wheeler", 
        "Middle_Name": "E.", 
        "Nickname": "", 
        "Phone": "", 
        "Suffix": ""
    }, 
    "4B03": {
        "Address": "601 Roxboro Place, NW; Washington, DC 20011", 
        "Email": "4B03@anc.dc.gov", 
        "First_Name": "Fred", 
        "Last_Name": "Grant", 
        "Middle_Name": "", 
        "Nickname": "", 
        "Phone": "", 
        "Suffix": ""
    }, 
    "4B04": {
        "Address": "6001 8th Street, NW; Washington, DC 20011", 
        "Email": "4B04@anc.dc.gov", 
        "First_Name": "Brenda", 
        "Last_Name": "Parks", 
        "Middle_Name": "", 
        "Nickname": "", 
        "Phone": "202-291-2557", 
        "Suffix": ""
    }, 
    "4B05": {
        "Address": "5700 4th Street, NW; Washington, DC 20011", 
        "Email": "4B05@anc.dc.gov", 
        "First_Name": "Brenda", 
        "Last_Name": "Speaks", 
        "Middle_Name": "", 
        "Nickname": "", 
        "Phone": "", 
        "Suffix": ""
    }, 
    "4B06": {
        "Address": "6120 North Dakota Avenue, NW; Washington, DC 20011", 
        "Email": "4B06@anc.dc.gov", 
        "First_Name": "Ronald", 
        "Last_Name": "Austin", 
        "Middle_Name": "", 
        "Nickname": "(Ron)", 
        "Phone": "", 
        "Suffix": ""
    }, 
    "4B07": {
        "Address": "25 Sheridan Street, NW; Washington, DC 20011", 
        "Email": "4B07@anc.dc.gov", 
        "First_Name": "Judi", 
        "Last_Name": "Jones", 
        "Middle_Name": "", 
        "Nickname": "", 
        "Phone": "", 
        "Suffix": ""
    }, 
    "4B08": {
        "Address": "6009 New Hampshire Avenue, NE; Washington, DC 20011", 
        "Email": "4B08@anc.dc.gov", 
        "First_Name": "Yvonne", 
        "Last_Name": "Jefferson", 
        "Middle_Name": "A.", 
        "Nickname": "", 
        "Phone": "", 
        "Suffix": ""
    }, 
    "4B09": {
        "Address": "313 Nicholson Street, NE; Washington, DC 20011", 
        "Email": "4B09@anc.dc.gov", 
        "First_Name": "Douglass", 
        "Last_Name": "Sloan", 
        "Middle_Name": "", 
        "Nickname": "", 
        "Phone": "202-455-3616", 
        "Suffix": ""
    }, 
    "4C01": {
        "Address": "1216 Madison Street, NW; Washington, DC 20011", 
        "Email": "4C01@anc.dc.gov", 
        "First_Name": "Michael", 
        "Last_Name": "Yates", 
        "Middle_Name": "", 
        "Nickname": "", 
        "Phone": "", 
        "Suffix": ""
    }, 
    "4C02": {
        "Address": "1403 Critenden Street NW ; Washington, 20011", 
        "Email": "4C02@anc.dc.gov", 
        "First_Name": "Joseph", 
        "Last_Name": "Maloney", 
        "Middle_Name": "", 
        "Nickname": "", 
        "Phone": "", 
        "Suffix": ""
    }, 
    "4C03": {
        "Address": "1127 Buchanan Street, NW; Washington, DC 20011", 
        "Email": "4C03@anc.dc.gov", 
        "First_Name": "Jeff", 
        "Last_Name": "Standish", 
        "Middle_Name": "", 
        "Nickname": "", 
        "Phone": "", 
        "Suffix": ""
    }, 
    "4C04": {
        "Address": "3900 14th Street, NW   Apt. 207; Washington, DC 20011", 
        "Email": "4C04@anc.dc.gov", 
        "First_Name": "Rickey", 
        "Last_Name": "Williams,", 
        "Middle_Name": "", 
        "Nickname": "", 
        "Phone": "202-290-7600", 
        "Suffix": "Jr."
    }, 
    "4C05": {
        "Address": "1305 Shepherd Street, NW; Washington, DC 20011", 
        "Email": "4C05@anc.dc.gov", 
        "First_Name": "Joseph", 
        "Last_Name": "Vaughan", 
        "Middle_Name": "M.", 
        "Nickname": "", 
        "Phone": "202-550-1081", 
        "Suffix": ""
    }, 
    "4C06": {
        "Address": "3809 13th Street, NW; Washington, DC 20011", 
        "Email": "4C06@anc.dc.gov", 
        "First_Name": "Vann-Di", 
        "Last_Name": "Galloway", 
        "Middle_Name": "", 
        "Nickname": "", 
        "Phone": "202-545-8155", 
        "Suffix": ""
    }, 
    "4C07": {
        "Address": "4409 Kansas Avenue, NW; Washington, DC 20011", 
        "Email": "4C07@anc.dc.gov", 
        "First_Name": "Shanel", 
        "Last_Name": "Anthony", 
        "Middle_Name": "O.", 
        "Nickname": "", 
        "Phone": "", 
        "Suffix": ""
    }, 
    "4C08": {
        "Address": "737 Rock Creek Church Road, NW ; Washington, DC 20010", 
        "Email": "4C08@anc.dc.gov", 
        "First_Name": "Timothy", 
        "Last_Name": "Jones", 
        "Middle_Name": "A.", 
        "Nickname": "", 
        "Phone": "202-722-0701", 
        "Suffix": ""
    }, 
    "4C09": {
        "Address": "117 Webster Street, NW; Washington, DC 20011", 
        "Email": "4C09@anc.dc.gov", 
        "First_Name": "Zachary", 
        "Last_Name": "Hartman", 
        "Middle_Name": "", 
        "Nickname": "", 
        "Phone": "202-505-1171", 
        "Suffix": ""
    }, 
    "4C10": {
        "Address": "112 Varnum Street NW; Washington, DC 20011", 
        "Email": "4C10@anc.dc.gov", 
        "First_Name": "Janell", 
        "Last_Name": "Rawlings", 
        "Middle_Name": "", 
        "Nickname": "", 
        "Phone": "", 
        "Suffix": ""
    }, 
    "4D01": {
        "Address": "738 Longfellow Street, NW; Washington, DC 20011", 
        "Email": "4D01@anc.dc.gov", 
        "First_Name": "Lamont", 
        "Last_Name": "Akins", 
        "Middle_Name": "", 
        "Nickname": "", 
        "Phone": "", 
        "Suffix": ""
    }, 
    "4D02": {
        "Address": "5322 2nd Street, NW; Washington, DC 20011", 
        "Email": "4D02@anc.dc.gov", 
        "First_Name": "Ren\u00e9e", 
        "Last_Name": "Bowser", 
        "Middle_Name": "L.", 
        "Nickname": "", 
        "Phone": "", 
        "Suffix": ""
    }, 
    "4D03": {
        "Address": "601 Gallatin Street, NW; Washington, DC 20001", 
        "Email": "4D03@anc.dc.gov", 
        "First_Name": "Lisa", 
        "Last_Name": "Colbert", 
        "Middle_Name": "", 
        "Nickname": "", 
        "Phone": "", 
        "Suffix": ""
    }, 
    "4D04": {
        "Address": "143 Kennedy Street, NW; Apt. 1; Washington, DC 20011", 
        "Email": "4D04@anc.dc.gov", 
        "First_Name": "Donna", 
        "Last_Name": "Brockington", 
        "Middle_Name": "", 
        "Nickname": "", 
        "Phone": "202-256-8733", 
        "Suffix": ""
    }, 
    "4D05": {
        "Address": "300 Emerson Street, NW; Washington, DC 20011", 
        "Email": "4D05@anc.dc.gov", 
        "First_Name": "Valikia", 
        "Last_Name": "Newsome", 
        "Middle_Name": "R.", 
        "Nickname": "", 
        "Phone": "", 
        "Suffix": ""
    }, 
    "4D06": {
        "Address": "143 Kennedy Street, NW; Apt. 1; Washington, DC 20011", 
        "Email": "4D06@anc.dc.gov", 
        "First_Name": "Bill", 
        "Last_Name": "Quirk", 
        "Middle_Name": "", 
        "Nickname": "", 
        "Phone": "", 
        "Suffix": ""
    }, 
    "5A01": {
        "Address": "5016 Eastern Avenue, NE; Washington, DC 20017", 
        "Email": "5A01@anc.dc.gov", 
        "First_Name": "Frank", 
        "Last_Name": "Wilds", 
        "Middle_Name": "", 
        "Nickname": "", 
        "Phone": "", 
        "Suffix": ""
    }, 
    "5A02": {
        "Address": "4945 Sargent Road, NE; Washington, DC 20017", 
        "Email": "5A02@anc.dc.gov", 
        "First_Name": "Grace", 
        "Last_Name": "Lewis", 
        "Middle_Name": "J.", 
        "Nickname": "", 
        "Phone": "", 
        "Suffix": ""
    }, 
    "5A03": {
        "Address": "4618 S. Dakota Avenue, NE; Washington, DC 20017", 
        "Email": "5A03@anc.dc.gov", 
        "First_Name": "Adrian", 
        "Last_Name": "Jordan", 
        "Middle_Name": "T.", 
        "Nickname": "", 
        "Phone": "", 
        "Suffix": ""
    }, 
    "5A04": {
        "Address": "", 
        "Email": "5A04@anc.dc.gov", 
        "First_Name": "vacant", 
        "Last_Name": "vacant", 
        "Middle_Name": "", 
        "Nickname": "", 
        "Phone": "", 
        "Suffix": ""
    }, 
    "5A05": {
        "Address": "122 Michigan Avenue, NE Apt L24; Washington, DC 20017", 
        "Email": "5A05@anc.dc.gov", 
        "First_Name": "Ronnie", 
        "Last_Name": "Edwards", 
        "Middle_Name": "", 
        "Nickname": "", 
        "Phone": "202-558-6389", 
        "Suffix": ""
    }, 
    "5A06": {
        "Address": "4530 Fort Totten Drive NE; Washington, DC 20011", 
        "Email": "5A06@anc.dc.gov", 
        "First_Name": "Jasmine", 
        "Last_Name": "White", 
        "Middle_Name": "N.", 
        "Nickname": "", 
        "Phone": "202-904-1919", 
        "Suffix": ""
    }, 
    "5A07": {
        "Address": "32 Buchanan Street, NE; Washington, DC 20011", 
        "Email": "5A07@anc.dc.gov", 
        "First_Name": "Sandra", 
        "Last_Name": "Washington", 
        "Middle_Name": "", 
        "Nickname": "\"Sandi\"", 
        "Phone": "", 
        "Suffix": ""
    }, 
    "5A08": {
        "Address": "4720 7th Street, NE; Washington, DC 20017", 
        "Email": "5A08@anc.dc.gov", 
        "First_Name": "Angel", 
        "Last_Name": "Alston", 
        "Middle_Name": "Sherri", 
        "Nickname": "", 
        "Phone": "", 
        "Suffix": ""
    }, 
    "5B01": {
        "Address": "2000 Upshur Street, NE; Washington, DC 20018", 
        "Email": "5B01@anc.dc.gov", 
        "First_Name": "Shirley", 
        "Last_Name": "Smith", 
        "Middle_Name": "Rivens", 
        "Nickname": "", 
        "Phone": "202-635-3138", 
        "Suffix": ""
    }, 
    "5B02": {
        "Address": "1902 Newton Street, NE; Washington, DC 20018", 
        "Email": "5B02@anc.dc.gov", 
        "First_Name": "Ursula", 
        "Last_Name": "Higgins", 
        "Middle_Name": "", 
        "Nickname": "", 
        "Phone": "", 
        "Suffix": ""
    }, 
    "5B03": {
        "Address": "1843 Monroe Street NE; Washington, DC 20018", 
        "Email": "5B03@anc.dc.gov", 
        "First_Name": "Michael", 
        "Last_Name": "Morrison", 
        "Middle_Name": "", 
        "Nickname": "", 
        "Phone": "", 
        "Suffix": ""
    }, 
    "5B04": {
        "Address": "1257 Lawrence Street, NE; Washington, DC 20017", 
        "Email": "5B04@anc.dc.gov", 
        "First_Name": "Carolyn", 
        "Last_Name": "Steptoe", 
        "Middle_Name": "C.", 
        "Nickname": "", 
        "Phone": "202-636-8191", 
        "Suffix": ""
    }, 
    "5B05": {
        "Address": "3919 9th Street, NE  Apt 1; Washington, DC 20017", 
        "Email": "5B05@anc.dc.gov", 
        "First_Name": "Jenese", 
        "Last_Name": "Jones", 
        "Middle_Name": "L.", 
        "Nickname": "", 
        "Phone": "", 
        "Suffix": ""
    }, 
    "5C01": {
        "Address": "2620 Rhode Island Avenue, NE; Washington, DC 20018", 
        "Email": "5C01@anc.dc.gov", 
        "First_Name": "Antonette", 
        "Last_Name": "Russell", 
        "Middle_Name": "E.", 
        "Nickname": "", 
        "Phone": "", 
        "Suffix": ""
    }, 
    "5C02": {
        "Address": "2214 Douglas Street, NE; Washington, DC 20018", 
        "Email": "5C02@anc.dc.gov", 
        "First_Name": "Karla", 
        "Last_Name": "Butler", 
        "Middle_Name": "", 
        "Nickname": "", 
        "Phone": "", 
        "Suffix": ""
    }, 
    "5C03": {
        "Address": "3102 Apple Road, NE; Washington, DC 20018", 
        "Email": "5C03@anc.dc.gov", 
        "First_Name": "Bob", 
        "Last_Name": "King", 
        "Middle_Name": "", 
        "Nickname": "", 
        "Phone": "", 
        "Suffix": ""
    }, 
    "5C04": {
        "Address": "2116 R Street, NE; Washington, DC 20002", 
        "Email": "5C04@anc.dc.gov", 
        "First_Name": "Jacqueline", 
        "Last_Name": "Manning", 
        "Middle_Name": "", 
        "Nickname": "", 
        "Phone": "", 
        "Suffix": ""
    }, 
    "5C05": {
        "Address": "1363 Adams Street, NE; Washington, DC 20018", 
        "Email": "5C05@anc.dc.gov", 
        "First_Name": "Regina", 
        "Last_Name": "James", 
        "Middle_Name": "", 
        "Nickname": "", 
        "Phone": "202-526-1681", 
        "Suffix": ""
    }, 
    "5C06": {
        "Address": "1448 Channing Street, NE; Washington, DC 20018", 
        "Email": "5C06@anc.dc.gov", 
        "First_Name": "Mercile", 
        "Last_Name": "Banks", 
        "Middle_Name": "", 
        "Nickname": "", 
        "Phone": "", 
        "Suffix": ""
    }, 
    "5C07": {
        "Address": "2222 Lawrence Street, NE; Washington, DC 20018", 
        "Email": "5C07@anc.dc.gov", 
        "First_Name": "Nolan", 
        "Last_Name": "Treadway", 
        "Middle_Name": "", 
        "Nickname": "", 
        "Phone": "", 
        "Suffix": ""
    }, 
    "5D01": {
        "Address": "1868 Corcoran Street, NE; Washington, DC 20002", 
        "Email": "5D01@anc.dc.gov", 
        "First_Name": "Peta-Gay", 
        "Last_Name": "Lewis", 
        "Middle_Name": "S.", 
        "Nickname": "", 
        "Phone": "", 
        "Suffix": ""
    }, 
    "5D02": {
        "Address": "1274 Holbrook Terrace, NE; Washington, DC 20002", 
        "Email": "5D02@anc.dc.gov", 
        "First_Name": "Vonetta", 
        "Last_Name": "Dumas", 
        "Middle_Name": "", 
        "Nickname": "", 
        "Phone": "", 
        "Suffix": ""
    }, 
    "5D03": {
        "Address": "1812 L Street, NE; Washington, DC 20002", 
        "Email": "5D03@anc.dc.gov", 
        "First_Name": "India", 
        "Last_Name": "Henderson", 
        "Middle_Name": "A.", 
        "Nickname": "", 
        "Phone": "202-397-2777", 
        "Suffix": ""
    }, 
    "5D04": {
        "Address": "2114 I Street, NE  (#103); Washington, DC 20002", 
        "Email": "5D04@anc.dc.gov", 
        "First_Name": "Bernice", 
        "Last_Name": "Blacknell", 
        "Middle_Name": "S", 
        "Nickname": "", 
        "Phone": "202-290-1024", 
        "Suffix": ""
    }, 
    "5D05": {
        "Address": "1807 L Street, NE; Washington, DC 20002", 
        "Email": "5D05@anc.dc.gov", 
        "First_Name": "Kathy", 
        "Last_Name": "Henderson", 
        "Middle_Name": "", 
        "Nickname": "", 
        "Phone": "", 
        "Suffix": ""
    }, 
    "5D06": {
        "Address": "1236 Florida Avenue, NE; Washington, DC 20002", 
        "Email": "5D06@anc.dc.gov", 
        "First_Name": "Tina", 
        "Last_Name": "Laskaris", 
        "Middle_Name": "", 
        "Nickname": "", 
        "Phone": "202-549-0153", 
        "Suffix": ""
    }, 
    "5D07": {
        "Address": "1324 Queen Street, NE; Washington, DC 20002", 
        "Email": "5D07@anc.dc.gov", 
        "First_Name": "David", 
        "Last_Name": "Hooper", 
        "Middle_Name": "", 
        "Nickname": "", 
        "Phone": "202-396-0788", 
        "Suffix": ""
    }, 
    "5E01": {
        "Address": "2826 6th Street, NE; Washington, DC 20017", 
        "Email": "5E01@anc.dc.gov", 
        "First_Name": "Debbie", 
        "Last_Name": "Smith-Steiner", 
        "Middle_Name": "", 
        "Nickname": "", 
        "Phone": "202-681-0095", 
        "Suffix": ""
    }, 
    "5E02": {
        "Address": "611 Edgewood Terrace, NE Apt 410; Washington, DC 20017", 
        "Email": "5E02@anc.dc.gov", 
        "First_Name": "Christy", 
        "Last_Name": "Davis", 
        "Middle_Name": "'Love'", 
        "Nickname": "", 
        "Phone": "202-525-4863", 
        "Suffix": ""
    }, 
    "5E03": {
        "Address": "302 T Street NE; Washington, DC 20002", 
        "Email": "5E03@anc.dc.gov", 
        "First_Name": "Alex", 
        "Last_Name": "Underwood", 
        "Middle_Name": "", 
        "Nickname": "", 
        "Phone": "", 
        "Suffix": ""
    }, 
    "5E04": {
        "Address": "34 R Street, NE; Washington, DC 20002", 
        "Email": "5E04@anc.dc.gov", 
        "First_Name": "Sylvia", 
        "Last_Name": "Pinkney", 
        "Middle_Name": "M.", 
        "Nickname": "", 
        "Phone": "", 
        "Suffix": ""
    }, 
    "5E05": {
        "Address": "16 N Street, NW; Washington, DC 20001", 
        "Email": "5E05@anc.dc.gov", 
        "First_Name": "Joyce", 
        "Last_Name": "Robinson-Paul", 
        "Middle_Name": "", 
        "Nickname": "", 
        "Phone": "", 
        "Suffix": ""
    }, 
    "5E06": {
        "Address": "1708 2nd Street, NW; Washington, DC 20001", 
        "Email": "5E06@anc.dc.gov", 
        "First_Name": "Teri", 
        "Last_Name": "Quinn", 
        "Middle_Name": "Janine", 
        "Nickname": "", 
        "Phone": "214-908-1913", 
        "Suffix": ""
    }, 
    "5E07": {
        "Address": "141 Randolph Place, NW; Washington, DC 20001", 
        "Email": "5E07@anc.dc.gov", 
        "First_Name": "Wanda", 
        "Last_Name": "Foster", 
        "Middle_Name": "B.", 
        "Nickname": "", 
        "Phone": "", 
        "Suffix": ""
    }, 
    "5E08": {
        "Address": "114 W Street, NW; Washington, DC 20001", 
        "Email": "5E08@anc.dc.gov", 
        "First_Name": "Mark", 
        "Last_Name": "Mueller", 
        "Middle_Name": "", 
        "Nickname": "", 
        "Phone": "202-200-3191", 
        "Suffix": ""
    }, 
    "5E09": {
        "Address": "41 Adams Street, NW; Washington, DC 20001", 
        "Email": "5E09@anc.dc.gov", 
        "First_Name": "C.", 
        "Last_Name": "Barnes", 
        "Middle_Name": "Dianne", 
        "Nickname": "", 
        "Phone": "", 
        "Suffix": ""
    }, 
    "5E10": {
        "Address": "223 Bryant Street, NE; Washington, DC 20002", 
        "Email": "5E10@anc.dc.gov", 
        "First_Name": "Angela", 
        "Last_Name": "Blanks", 
        "Middle_Name": "", 
        "Nickname": "", 
        "Phone": "", 
        "Suffix": ""
    }, 
    "6A01": {
        "Address": "718 10th Street NE; Washington, DC 20002", 
        "Email": "6A01@anc.dc.gov", 
        "First_Name": "J.", 
        "Last_Name": "Mahmud", 
        "Middle_Name": "Omar", 
        "Nickname": "", 
        "Phone": "", 
        "Suffix": ""
    }, 
    "6A02": {
        "Address": "1239 Maryland Avenue NE; Washington, DC 20002", 
        "Email": "6A02@anc.dc.gov", 
        "First_Name": "Gloria", 
        "Last_Name": "Nauden", 
        "Middle_Name": "", 
        "Nickname": "", 
        "Phone": "", 
        "Suffix": ""
    }, 
    "6A03": {
        "Address": "919 Massachusetts Avenue NE; Washington, DC 20002", 
        "Email": "6A03@anc.dc.gov", 
        "First_Name": "David", 
        "Last_Name": "Holmes", 
        "Middle_Name": "", 
        "Nickname": "", 
        "Phone": "", 
        "Suffix": ""
    }, 
    "6A04": {
        "Address": "1330 North Carolina Avenue NE; Washington, DC 20002", 
        "Email": "6A04@anc.dc.gov", 
        "First_Name": "Nickolas", 
        "Last_Name": "Alberti", 
        "Middle_Name": "", 
        "Nickname": "", 
        "Phone": "202-329-1193", 
        "Suffix": ""
    }, 
    "6A05": {
        "Address": "315 12th Street NE; Washington, DC 20002", 
        "Email": "6A05@anc.dc.gov", 
        "First_Name": "Jay", 
        "Last_Name": "Williams", 
        "Middle_Name": "", 
        "Nickname": "", 
        "Phone": "202-906-0657", 
        "Suffix": ""
    }, 
    "6A06": {
        "Address": "1364 Emerald Street NE; Washington, DC 20002", 
        "Email": "6A06@anc.dc.gov", 
        "First_Name": "Andrew", 
        "Last_Name": "Hysell", 
        "Middle_Name": "J", 
        "Nickname": "", 
        "Phone": "", 
        "Suffix": ""
    }, 
    "6A07": {
        "Address": "1744 E Street NE; Washington, DC 20002", 
        "Email": "6A07@anc.dc.gov", 
        "First_Name": "Sondra", 
        "Last_Name": "Phillips-Gilbert", 
        "Middle_Name": "", 
        "Nickname": "", 
        "Phone": "202-397-7228", 
        "Suffix": ""
    }, 
    "6A08": {
        "Address": "436 19th Street NE;  Washington, DC 20002", 
        "Email": "6A08@anc.dc.gov", 
        "First_Name": "Calvin", 
        "Last_Name": "Ward", 
        "Middle_Name": "", 
        "Nickname": "", 
        "Phone": "", 
        "Suffix": ""
    }, 
    "6B01": {
        "Address": "8 - 4th Street SE; Washington, DC 20003", 
        "Email": "6B01@anc.dc.gov", 
        "First_Name": "David", 
        "Last_Name": "Garrison", 
        "Middle_Name": "", 
        "Nickname": "", 
        "Phone": "", 
        "Suffix": ""
    }, 
    "6B02": {
        "Address": "620 D Street SE; Washington, DC 20003", 
        "Email": "6B02@anc.dc.gov", 
        "First_Name": "Ivan", 
        "Last_Name": "Frishberg", 
        "Middle_Name": "", 
        "Nickname": "", 
        "Phone": "202-487-6064", 
        "Suffix": ""
    }, 
    "6B03": {
        "Address": "506 G Street SE; Washington, DC 20003", 
        "Email": "6B03@anc.dc.gov", 
        "First_Name": "Phil", 
        "Last_Name": "Peisch", 
        "Middle_Name": "", 
        "Nickname": "", 
        "Phone": "(339) 927-6908", 
        "Suffix": ""
    }, 
    "6B04": {
        "Address": "423 12th Street SE; Washington, DC 20003", 
        "Email": "6B04@anc.dc.gov", 
        "First_Name": "Kirsten", 
        "Last_Name": "Oldenburg", 
        "Middle_Name": "", 
        "Nickname": "", 
        "Phone": "202-546-8542", 
        "Suffix": ""
    }, 
    "6B05": {
        "Address": "111 13th Street SE; Washington, DC 20003", 
        "Email": "6B05@anc.dc.gov", 
        "First_Name": "Brian", 
        "Last_Name": "Pate", 
        "Middle_Name": "", 
        "Nickname": "", 
        "Phone": "202-821-7109", 
        "Suffix": ""
    }, 
    "6B06": {
        "Address": "542 14th Street SE; Washington, DC 20003", 
        "Email": "6B06@anc.dc.gov", 
        "First_Name": "Nichole", 
        "Last_Name": "Opkins", 
        "Middle_Name": "", 
        "Nickname": "", 
        "Phone": "", 
        "Suffix": ""
    }, 
    "6B07": {
        "Address": "951 14th Street SE; Washington, DC 20003", 
        "Email": "6B07@anc.dc.gov", 
        "First_Name": "Sara", 
        "Last_Name": "Loveland", 
        "Middle_Name": "", 
        "Nickname": "", 
        "Phone": "202-330-8745", 
        "Suffix": ""
    }, 
    "6B08": {
        "Address": "1436 Independence Avenue SE;  Washington, DC 20003", 
        "Email": "6B08@anc.dc.gov", 
        "First_Name": "Chander", 
        "Last_Name": "Jayaraman", 
        "Middle_Name": "", 
        "Nickname": "", 
        "Phone": "202-546-2609", 
        "Suffix": ""
    }, 
    "6B09": {
        "Address": "1628 Potomac Avenue SE;  Washington, DC 20003", 
        "Email": "6B09@anc.dc.gov", 
        "First_Name": "Brian", 
        "Last_Name": "Flahaven", 
        "Middle_Name": "", 
        "Nickname": "", 
        "Phone": "", 
        "Suffix": ""
    }, 
    "6B10": {
        "Address": "1800 Burke Street SE;  Washington, DC 20003", 
        "Email": "6B10@anc.dc.gov", 
        "First_Name": "Francis", 
        "Last_Name": "Campbell", 
        "Middle_Name": "M.", 
        "Nickname": "", 
        "Phone": "", 
        "Suffix": ""
    }, 
    "6C01": {
        "Address": "19 7th Street NE; Washington, DC 20002", 
        "Email": "6C01@anc.dc.gov", 
        "First_Name": "Daniele", 
        "Last_Name": "Schiffman", 
        "Middle_Name": "Megan", 
        "Nickname": "", 
        "Phone": "", 
        "Suffix": ""
    }, 
    "6C02": {
        "Address": "234 E Street NE; Washington, DC 20002", 
        "Email": "6C02@anc.dc.gov", 
        "First_Name": "Karen", 
        "Last_Name": "Wirt", 
        "Middle_Name": "J.", 
        "Nickname": "", 
        "Phone": "202-547-7168", 
        "Suffix": ""
    }, 
    "6C03": {
        "Address": "517 E Street NE; Washington, DC 20002", 
        "Email": "6C03@anc.dc.gov", 
        "First_Name": "John", 
        "Last_Name": "Price", 
        "Middle_Name": "Scott", 
        "Nickname": "", 
        "Phone": "202-577-6261", 
        "Suffix": ""
    }, 
    "6C04": {
        "Address": "312 E Street NE; Washington, DC 20002", 
        "Email": "6C04@anc.dc.gov", 
        "First_Name": "Mark", 
        "Last_Name": "Eckenwiler", 
        "Middle_Name": "", 
        "Nickname": "", 
        "Phone": "202-546-8542", 
        "Suffix": ""
    }, 
    "6C05": {
        "Address": "829 5th Street NE; Washington, DC 20002", 
        "Email": "6C05@anc.dc.gov", 
        "First_Name": "Mark", 
        "Last_Name": "Kazmierczak", 
        "Middle_Name": "", 
        "Nickname": "", 
        "Phone": "202-455-6305", 
        "Suffix": ""
    }, 
    "6C06": {
        "Address": "1152 4th Street NE; Washington, DC 20002", 
        "Email": "6C06@anc.dc.gov", 
        "First_Name": "Tony", 
        "Last_Name": "Goodman", 
        "Middle_Name": "T", 
        "Nickname": "", 
        "Phone": "", 
        "Suffix": ""
    }, 
    "6D01": {
        "Address": "907 6th Street SW; Washington, DC 20024", 
        "Email": "6D01@anc.dc.gov", 
        "First_Name": "Sam", 
        "Last_Name": "Marrero", 
        "Middle_Name": "", 
        "Nickname": "", 
        "Phone": "", 
        "Suffix": ""
    }, 
    "6D02": {
        "Address": "Washington, DC 20003", 
        "Email": "6D02@anc.dc.gov", 
        "First_Name": "Vacant", 
        "Last_Name": "Vacant", 
        "Middle_Name": "", 
        "Nickname": "", 
        "Phone": "", 
        "Suffix": ""
    }, 
    "6D03": {
        "Address": "800 4th Street SW; Washington, DC 20024", 
        "Email": "6D03@anc.dc.gov", 
        "First_Name": "Rachel", 
        "Last_Name": "Carroll", 
        "Middle_Name": "Reilly", 
        "Nickname": "", 
        "Phone": "", 
        "Suffix": ""
    }, 
    "6D04": {
        "Address": "423 N Street SW; Washington, DC 20024", 
        "Email": "6D04@anc.dc.gov", 
        "First_Name": "Andy", 
        "Last_Name": "Litsky", 
        "Middle_Name": "", 
        "Nickname": "", 
        "Phone": "", 
        "Suffix": ""
    }, 
    "6D05": {
        "Address": "1301 Delaware Avenue SW; Washington, DC 20024", 
        "Email": "6D05@anc.dc.gov", 
        "First_Name": "Roger", 
        "Last_Name": "Moffatt", 
        "Middle_Name": "", 
        "Nickname": "", 
        "Phone": "", 
        "Suffix": ""
    }, 
    "6D06": {
        "Address": "44 O Street SW; Washington, DC 20024", 
        "Email": "6D06@anc.dc.gov", 
        "First_Name": "Rhonda", 
        "Last_Name": "Hamilton", 
        "Middle_Name": "N.", 
        "Nickname": "", 
        "Phone": "", 
        "Suffix": ""
    }, 
    "6D07": {
        "Address": "1100 1st Street SE; Washington, DC 20024", 
        "Email": "6D07@anc.dc.gov", 
        "First_Name": "David", 
        "Last_Name": "Garber", 
        "Middle_Name": "", 
        "Nickname": "", 
        "Phone": "202-642-5811", 
        "Suffix": ""
    }, 
    "6E01": {
        "Address": "1519 8th Street NW; Washington, DC 20001", 
        "Email": "6E01@anc.dc.gov", 
        "First_Name": "Alexander", 
        "Last_Name": "Padro", 
        "Middle_Name": "M.", 
        "Nickname": "\"Alex\"", 
        "Phone": "202-518-3794", 
        "Suffix": ""
    }, 
    "6E02": {
        "Address": "438 S Steet NW; Washington, DC 20001", 
        "Email": "6E02@anc.dc.gov", 
        "First_Name": "Kevin", 
        "Last_Name": "Chapple", 
        "Middle_Name": "", 
        "Nickname": "", 
        "Phone": "202-449-5072", 
        "Suffix": ""
    }, 
    "6E03": {
        "Address": "1340 5th Street NW; Washington, DC 20001", 
        "Email": "6E03@anc.dc.gov", 
        "First_Name": "Frank", 
        "Last_Name": "Wiggins", 
        "Middle_Name": "S.", 
        "Nickname": "", 
        "Phone": "", 
        "Suffix": ""
    }, 
    "6E04": {
        "Address": "437 New York Avenue NW; Washington, DC 20001", 
        "Email": "6E04@anc.dc.gov", 
        "First_Name": "Rachelle", 
        "Last_Name": "Nigro", 
        "Middle_Name": "P.", 
        "Nickname": "", 
        "Phone": "202-670-1732", 
        "Suffix": ""
    }, 
    "6E05": {
        "Address": "475 K Street NW; Washington, DC 20001", 
        "Email": "6E05@anc.dc.gov", 
        "First_Name": "Marge", 
        "Last_Name": "Maceda", 
        "Middle_Name": "", 
        "Nickname": "", 
        "Phone": "202-360-7404", 
        "Suffix": ""
    }, 
    "6E06": {
        "Address": "40 New York Avenue NW; Washington, DC 20001", 
        "Email": "6E06@anc.dc.gov", 
        "First_Name": "Alvin", 
        "Last_Name": "Judd,", 
        "Middle_Name": "O.", 
        "Nickname": "", 
        "Phone": "(301) 440-3836", 
        "Suffix": "Sr."
    }, 
    "6E07": {
        "Address": "117 Pierce Street NW; Washington, DC 20001", 
        "Email": "6E07@anc.dc.gov", 
        "First_Name": "Alfreda", 
        "Last_Name": "Judd", 
        "Middle_Name": "S.", 
        "Nickname": "", 
        "Phone": "", 
        "Suffix": ""
    }, 
    "7B01": {
        "Address": "2936 M Street, SE; Washington, DC 20019", 
        "Email": "7B01@anc.dc.gov", 
        "First_Name": "Patricia", 
        "Last_Name": "Howard-Chittams", 
        "Middle_Name": "", 
        "Nickname": "", 
        "Phone": "", 
        "Suffix": ""
    }, 
    "7B02": {
        "Address": "2540 Naylor Road, SE; Apt. 301; Washington, DC 20020", 
        "Email": "7B02@anc.dc.gov", 
        "First_Name": "Zina", 
        "Last_Name": "Williams", 
        "Middle_Name": "D.", 
        "Nickname": "", 
        "Phone": "202-327-1455", 
        "Suffix": ""
    }, 
    "7B03": {
        "Address": "2424 L'Enfant Square, SE; Washington, DC 20020", 
        "Email": "7B03@anc.dc.gov", 
        "First_Name": "Gary", 
        "Last_Name": "Butler", 
        "Middle_Name": "", 
        "Nickname": "", 
        "Phone": "", 
        "Suffix": ""
    }, 
    "7B04": {
        "Address": "2132 Branch Avenue, SE; Washington, DC 20020", 
        "Email": "7B04@anc.dc.gov", 
        "First_Name": "Phillip", 
        "Last_Name": "Hammond", 
        "Middle_Name": "J.", 
        "Nickname": "", 
        "Phone": "", 
        "Suffix": ""
    }, 
    "7B05": {
        "Address": "3200 S Street, SE; Washington, DC 20020", 
        "Email": "7B05@anc.dc.gov", 
        "First_Name": "Robin", 
        "Last_Name": "Marlin", 
        "Middle_Name": "Hammond", 
        "Nickname": "", 
        "Phone": "", 
        "Suffix": ""
    }, 
    "7B06": {
        "Address": "3901 Pennsylvania Avenue, SE; Apt. A; Washington, DC 20020", 
        "Email": "7B06@anc.dc.gov", 
        "First_Name": "Robert", 
        "Last_Name": "Jordan", 
        "Middle_Name": "A.", 
        "Nickname": "", 
        "Phone": "", 
        "Suffix": ""
    }, 
    "7B07": {
        "Address": "3524 Carpenter Street, SE; Washington, DC 20020", 
        "Email": "7B07@anc.dc.gov", 
        "First_Name": "Robert", 
        "Last_Name": "Richards", 
        "Middle_Name": "T.", 
        "Nickname": "", 
        "Phone": "202-583-3524", 
        "Suffix": ""
    }, 
    "7C01": {
        "Address": "501 50th Place, NE; Washington, DC 20019", 
        "Email": "7C01@anc.dc.gov", 
        "First_Name": "Patricia", 
        "Last_Name": "Malloy", 
        "Middle_Name": "A.", 
        "Nickname": "", 
        "Phone": "", 
        "Suffix": ""
    }, 
    "7C02": {
        "Address": "5364 Ames Street ,NE; Washington, DC 20019", 
        "Email": "7C02@anc.dc.gov", 
        "First_Name": "Greg", 
        "Last_Name": "Stewart", 
        "Middle_Name": "", 
        "Nickname": "", 
        "Phone": "202-505-1167", 
        "Suffix": ""
    }, 
    "7C03": {
        "Address": "4904 Fitch Place, NE; Washington, DC 20019", 
        "Email": "7C03@anc.dc.gov", 
        "First_Name": "Catherine", 
        "Last_Name": "Woods", 
        "Middle_Name": "A.", 
        "Nickname": "", 
        "Phone": "", 
        "Suffix": ""
    }, 
    "7C04": {
        "Address": "4605 Hunt Place, NE; Washington, DC 20019", 
        "Email": "7C04@anc.dc.gov", 
        "First_Name": "Walter", 
        "Last_Name": "Garcia,", 
        "Middle_Name": "Garcia", 
        "Nickname": "", 
        "Phone": "202-251-0783", 
        "Suffix": "II"
    }, 
    "7C05": {
        "Address": "328 62nd Street, NE; Apt. 201; Washington, DC 20019", 
        "Email": "7C05@anc.dc.gov", 
        "First_Name": "Mary", 
        "Last_Name": "Gaffney", 
        "Middle_Name": "L.", 
        "Nickname": "", 
        "Phone": "", 
        "Suffix": ""
    }, 
    "7C06": {
        "Address": "944 Eastern Avenue, NE; Apt. 12; Washington, DC 20019", 
        "Email": "7C06@anc.dc.gov", 
        "First_Name": "Sherrie", 
        "Last_Name": "Lawson", 
        "Middle_Name": "", 
        "Nickname": "", 
        "Phone": "", 
        "Suffix": ""
    }, 
    "7C07": {
        "Address": "4805 Meade Street, NE; Washington, DC 20019", 
        "Email": "7C07@anc.dc.gov", 
        "First_Name": "Antawan", 
        "Last_Name": "Holmes", 
        "Middle_Name": "", 
        "Nickname": "", 
        "Phone": "202-556-0962", 
        "Suffix": ""
    }, 
    "7D01": {
        "Address": "554 25th Place, NE; Washington, DC 20019", 
        "Email": "7D01@anc.dc.gov", 
        "First_Name": "Lisa", 
        "Last_Name": "White", 
        "Middle_Name": "", 
        "Nickname": "", 
        "Phone": "202-706-4713", 
        "Suffix": ""
    }, 
    "7D02": {
        "Address": "4004 Meade Street, NE; Washington, DC 2001", 
        "Email": "7D02@anc.dc.gov", 
        "First_Name": "Dan", 
        "Last_Name": "Milstein", 
        "Middle_Name": "", 
        "Nickname": "", 
        "Phone": "", 
        "Suffix": ""
    }, 
    "7D03": {
        "Address": "4406 Quarles Street, NE; Washington, DC 20019", 
        "Email": "7D03@anc.dc.gov", 
        "First_Name": "Donna", 
        "Last_Name": "Muhammad", 
        "Middle_Name": "R.", 
        "Nickname": "", 
        "Phone": "202-398-8806", 
        "Suffix": ""
    }, 
    "7D04": {
        "Address": "313 34th Place, NE; Washington, DC 20019", 
        "Email": "7D04@anc.dc.gov", 
        "First_Name": "Jo-Anne", 
        "Last_Name": "Prue", 
        "Middle_Name": "", 
        "Nickname": "", 
        "Phone": "", 
        "Suffix": ""
    }, 
    "7D05": {
        "Address": "34 46th Place, NE; Washington, DC 20019", 
        "Email": "7D05@anc.dc.gov", 
        "First_Name": "Janis", 
        "Last_Name": "Hazel", 
        "Middle_Name": "D.", 
        "Nickname": "", 
        "Phone": "202-630-5099", 
        "Suffix": ""
    }, 
    "7D06": {
        "Address": "4058 Minnesota Avenue, NE; Washington, DC 20019", 
        "Email": "7D06@anc.dc.gov", 
        "First_Name": "Ericka", 
        "Last_Name": "Black", 
        "Middle_Name": "S.", 
        "Nickname": "", 
        "Phone": "202-670-6677", 
        "Suffix": ""
    }, 
    "7D07": {
        "Address": "3725 Cassell Place, NE; Washington, DC 20019", 
        "Email": "7D07@anc.dc.gov", 
        "First_Name": "Willie", 
        "Last_Name": "Woods,", 
        "Middle_Name": "Woods", 
        "Nickname": "", 
        "Phone": "202-322-1912", 
        "Suffix": "Jr."
    }, 
    "7E01": {
        "Address": "4535 Alabama Avenue, SE; Washington, DC 20019", 
        "Email": "7E01@anc.dc.gov", 
        "First_Name": "George", 
        "Last_Name": "Browne,", 
        "Middle_Name": "Browne", 
        "Nickname": "", 
        "Phone": "", 
        "Suffix": "Jr."
    }, 
    "7E02": {
        "Address": "4239 Massachusetts Avenue, SE; Washington, DC 20019", 
        "Email": "7E02@anc.dc.gov", 
        "First_Name": "Linda", 
        "Last_Name": "Green", 
        "Middle_Name": "S.", 
        "Nickname": "", 
        "Phone": "202-354-1861", 
        "Suffix": ""
    }, 
    "7E03": {
        "Address": "503 53rd Street ,SE; Washington, DC 20019", 
        "Email": "7E03@anc.dc.gov", 
        "First_Name": "Rosa", 
        "Last_Name": "Hamlett", 
        "Middle_Name": "A.", 
        "Nickname": "", 
        "Phone": "", 
        "Suffix": ""
    }, 
    "7E04": {
        "Address": "135 49th Street, SE; Washington, DC 20019", 
        "Email": "7E04@anc.dc.gov", 
        "First_Name": "Mary", 
        "Last_Name": "Jackson", 
        "Middle_Name": "D.", 
        "Nickname": "", 
        "Phone": "", 
        "Suffix": ""
    }, 
    "7E05": {
        "Address": "4901 Astor Place, SE; Washington, DC 20019", 
        "Email": "7E05@anc.dc.gov", 
        "First_Name": "Jean", 
        "Last_Name": "McVea", 
        "Middle_Name": "M.", 
        "Nickname": "", 
        "Phone": "202-409-8914", 
        "Suffix": ""
    }, 
    "7E06": {
        "Address": "5561 Central Avenue ,SE; Washington, DC 20019", 
        "Email": "7E06@anc.dc.gov", 
        "First_Name": "Joseph", 
        "Last_Name": "Lockett", 
        "Middle_Name": "Wayne", 
        "Nickname": "", 
        "Phone": "", 
        "Suffix": ""
    }, 
    "7E07": {
        "Address": "30 58th Street SE; Washington, DC 20019", 
        "Email": "7E07@anc.dc.gov", 
        "First_Name": "Wendell", 
        "Last_Name": "Felder", 
        "Middle_Name": "", 
        "Nickname": "", 
        "Phone": "", 
        "Suffix": ""
    }, 
    "7F01": {
        "Address": "3938 East Capitol Street, NE; Washington, DC 20019", 
        "Email": "7F01@anc.dc.gov", 
        "First_Name": "Evie", 
        "Last_Name": "Washington", 
        "Middle_Name": "L.", 
        "Nickname": "", 
        "Phone": "202-396-7791", 
        "Suffix": ""
    }, 
    "7F02": {
        "Address": "4562 Texas Avenue, SE; Washington, DC 20019", 
        "Email": "7F02@anc.dc.gov", 
        "First_Name": "Eboni-Rose", 
        "Last_Name": "Thompson", 
        "Middle_Name": "", 
        "Nickname": "", 
        "Phone": "", 
        "Suffix": ""
    }, 
    "7F03": {
        "Address": "515 46th Street ,SE; Washington, DC 20019", 
        "Email": "7F03@anc.dc.gov", 
        "First_Name": "Sheila", 
        "Last_Name": "Carr", 
        "Middle_Name": "Carson", 
        "Nickname": "", 
        "Phone": "202-904-3374", 
        "Suffix": ""
    }, 
    "7F04": {
        "Address": "3423 Minnesota Avenue, SE; Washington, DC 20019", 
        "Email": "7F04@anc.dc.gov", 
        "First_Name": "Charlene", 
        "Last_Name": "Exum", 
        "Middle_Name": "", 
        "Nickname": "", 
        "Phone": "", 
        "Suffix": ""
    }, 
    "7F05": {
        "Address": "234 37th Street, SE; Washington, DC 20019", 
        "Email": "7F05@anc.dc.gov", 
        "First_Name": "Karen", 
        "Last_Name": "Settles", 
        "Middle_Name": "", 
        "Nickname": "", 
        "Phone": "", 
        "Suffix": ""
    }, 
    "7F06": {
        "Address": "3444 Croffut Place, SE; Washington, DC 20019", 
        "Email": "7F06@anc.dc.gov", 
        "First_Name": "Elizabeth", 
        "Last_Name": "Travers", 
        "Middle_Name": "H.", 
        "Nickname": "", 
        "Phone": "", 
        "Suffix": ""
    }, 
    "7F07": {
        "Address": "", 
        "Email": "7F07@anc.dc.gov", 
        "First_Name": "Vacant", 
        "Last_Name": "Vacant", 
        "Middle_Name": "", 
        "Nickname": "", 
        "Phone": "", 
        "Suffix": ""
    }, 
    "8A01": {
        "Address": "1936 Naylor Road SE (102); Washington, DC 20020", 
        "Email": "8A01@anc.dc.gov", 
        "First_Name": "Holly", 
        "Last_Name": "Muhammad", 
        "Middle_Name": "", 
        "Nickname": "", 
        "Phone": "", 
        "Suffix": ""
    }, 
    "8A02": {
        "Address": "1620 Ridge Place SE; Washington, DC 20020", 
        "Email": "8A02@anc.dc.gov", 
        "First_Name": "Barbara", 
        "Last_Name": "Clark", 
        "Middle_Name": "J.", 
        "Nickname": "", 
        "Phone": "", 
        "Suffix": ""
    }, 
    "8A03": {
        "Address": "2330 Good Hope Road SE  Apt. 1112; Washington, DC 20020", 
        "Email": "8A03@anc.dc.gov", 
        "First_Name": "L.", 
        "Last_Name": "Moore", 
        "Middle_Name": "Yvonne", 
        "Nickname": "(L.Y.)", 
        "Phone": "", 
        "Suffix": ""
    }, 
    "8A04": {
        "Address": "2318 16th Street SE   Apt. 6; Washington, DC 20020", 
        "Email": "8A04@anc.dc.gov", 
        "First_Name": "Moses", 
        "Last_Name": "Smith", 
        "Middle_Name": "", 
        "Nickname": "", 
        "Phone": "", 
        "Suffix": ""
    }, 
    "8A05": {
        "Address": "1643 U Street SE; Washington, DC 20020", 
        "Email": "8A05@anc.dc.gov", 
        "First_Name": "Charles", 
        "Last_Name": "Wilson", 
        "Middle_Name": "E.", 
        "Nickname": "", 
        "Phone": "202-556-5090", 
        "Suffix": ""
    }, 
    "8A06": {
        "Address": "1352 Maple Pl SE; Washington, DC 20020", 
        "Email": "8A06@anc.dc.gov", 
        "First_Name": "Greta", 
        "Last_Name": "Fuller", 
        "Middle_Name": "", 
        "Nickname": "", 
        "Phone": "", 
        "Suffix": ""
    }, 
    "8A07": {
        "Address": "2619 Douglass Place SE  Apt 403; Washington, DC 20020", 
        "Email": "8A07@anc.dc.gov", 
        "First_Name": "Natalie", 
        "Last_Name": "Williams", 
        "Middle_Name": "", 
        "Nickname": "", 
        "Phone": "", 
        "Suffix": ""
    }, 
    "8B01": {
        "Address": "2437 Wagner Street SE; Washington, DC 20013", 
        "Email": "8B01@anc.dc.gov", 
        "First_Name": "Khadijah", 
        "Last_Name": "Watson", 
        "Middle_Name": "", 
        "Nickname": "", 
        "Phone": "202-610-4077", 
        "Suffix": ""
    }, 
    "8B02": {
        "Address": "P.O. Box 30497; Washington, DC 20030", 
        "Email": "8B02@anc.dc.gov", 
        "First_Name": "Darrell", 
        "Last_Name": "Gaston", 
        "Middle_Name": "Danny", 
        "Nickname": "", 
        "Phone": "", 
        "Suffix": ""
    }, 
    "8B03": {
        "Address": "1808 Morris Road SE; Washington, DC 20020", 
        "Email": "8B03@anc.dc.gov", 
        "First_Name": "Charles", 
        "Last_Name": "Wilson", 
        "Middle_Name": "H.", 
        "Nickname": "", 
        "Phone": "", 
        "Suffix": ""
    }, 
    "8B04": {
        "Address": "1600 Frankford Street SE  Apt. 101; Washington, DC 20020", 
        "Email": "8B04@anc.dc.gov", 
        "First_Name": "Anthony", 
        "Last_Name": "Green", 
        "Middle_Name": "Lorenzo", 
        "Nickname": "", 
        "Phone": "202-709-8091", 
        "Suffix": ""
    }, 
    "8B05": {
        "Address": "2740 Knox Terrace SE; Washington, DC 20020", 
        "Email": "8B05@anc.dc.gov", 
        "First_Name": "Betty", 
        "Last_Name": "Scippio", 
        "Middle_Name": "", 
        "Nickname": "", 
        "Phone": "", 
        "Suffix": ""
    }, 
    "8B06": {
        "Address": "3406 23rd Street SE; Washington, DC 20020", 
        "Email": "8B06@anc.dc.gov", 
        "First_Name": "Mitchell", 
        "Last_Name": "Hawkins,", 
        "Middle_Name": "Hawkins", 
        "Nickname": "", 
        "Phone": "", 
        "Suffix": "III"
    }, 
    "8B07": {
        "Address": "1924 Trenton Place SE; Washington, DC 20020", 
        "Email": "8B07@anc.dc.gov", 
        "First_Name": "Louise", 
        "Last_Name": "Thorne", 
        "Middle_Name": "", 
        "Nickname": "", 
        "Phone": "", 
        "Suffix": ""
    }, 
    "8C01": {
        "Address": "3361 Brothers Place SE; Washington, DC 20032", 
        "Email": "8C01@anc.dc.gov", 
        "First_Name": "Jeffrey", 
        "Last_Name": "McCoy", 
        "Middle_Name": "", 
        "Nickname": "", 
        "Phone": "", 
        "Suffix": ""
    }, 
    "8C02": {
        "Address": "3109 Martin Luther King Avenue SE; Washington, DC 20020", 
        "Email": "8C02@anc.dc.gov", 
        "First_Name": "Teresa", 
        "Last_Name": "Stith", 
        "Middle_Name": "A.", 
        "Nickname": "", 
        "Phone": "", 
        "Suffix": ""
    }, 
    "8C03": {
        "Address": "3325 Martin Luther King Ave SE APT. 12; Washington, DC 20032", 
        "Email": "8C03@anc.dc.gov", 
        "First_Name": "Mary", 
        "Last_Name": "Cuthbert", 
        "Middle_Name": "", 
        "Nickname": "", 
        "Phone": "202-246-9410", 
        "Suffix": ""
    }, 
    "8C04": {
        "Address": "158 Xenia Street; Washington, DC 20032", 
        "Email": "8C04@anc.dc.gov", 
        "First_Name": "Derrick", 
        "Last_Name": "Colbert", 
        "Middle_Name": "A.", 
        "Nickname": "", 
        "Phone": "202-905-8810", 
        "Suffix": ""
    }, 
    "8C05": {
        "Address": "3630 Brothers Place SE; Washington, DC 20032", 
        "Email": "8C05@anc.dc.gov", 
        "First_Name": "Lloyd", 
        "Last_Name": "Logan", 
        "Middle_Name": "T.", 
        "Nickname": "", 
        "Phone": "", 
        "Suffix": ""
    }, 
    "8C06": {
        "Address": "P.O. Box 62695; Washington, DC 20029", 
        "Email": "8C06@anc.dc.gov", 
        "First_Name": "Naomi", 
        "Last_Name": "Carthens", 
        "Middle_Name": "", 
        "Nickname": "", 
        "Phone": "", 
        "Suffix": ""
    }, 
    "8C07": {
        "Address": "P.O. Box 30833; Washington, DC 20030", 
        "Email": "8C07@anc.dc.gov", 
        "First_Name": "Pho", 
        "Last_Name": "Palmer", 
        "Middle_Name": "", 
        "Nickname": "", 
        "Phone": "", 
        "Suffix": ""
    }, 
    "8D01": {
        "Address": "816 Southern AVE SE APT 214; Washington, DC 20032", 
        "Email": "8D01@anc.dc.gov", 
        "First_Name": "Patricia", 
        "Last_Name": "Carmon", 
        "Middle_Name": "", 
        "Nickname": "", 
        "Phone": "202-431-1699", 
        "Suffix": ""
    }, 
    "8D02": {
        "Address": "4612 6th Street SE; Washington, DC 20032", 
        "Email": "8D02@anc.dc.gov", 
        "First_Name": "Olivia", 
        "Last_Name": "Henderson", 
        "Middle_Name": "L.", 
        "Nickname": "", 
        "Phone": "", 
        "Suffix": ""
    }, 
    "8D03": {
        "Address": "4335 4th Street SE APT 3; Washington, DC 20032", 
        "Email": "8D03@anc.dc.gov", 
        "First_Name": "Absalom", 
        "Last_Name": "Jordan", 
        "Middle_Name": "", 
        "Nickname": "", 
        "Phone": "", 
        "Suffix": ""
    }, 
    "8D04": {
        "Address": "136 Ivanhoe Street SW APT 101; Washington DC 20032", 
        "Email": "8D04@anc.dc.gov", 
        "First_Name": "M.", 
        "Last_Name": "Lee", 
        "Middle_Name": "Jay", 
        "Nickname": "", 
        "Phone": "", 
        "Suffix": ""
    }, 
    "8D05": {
        "Address": "153 Galveston Place SE APT 4; Washington, DC 20032", 
        "Email": "8D05@anc.dc.gov", 
        "First_Name": "Thomas", 
        "Last_Name": "Ruffin,", 
        "Middle_Name": "", 
        "Nickname": "", 
        "Phone": "", 
        "Suffix": "Jr."
    }, 
    "8D06": {
        "Address": "142 Elmira Street SW; Washington DC 20032", 
        "Email": "8D06@anc.dc.gov", 
        "First_Name": "Thea", 
        "Last_Name": "Dyson", 
        "Middle_Name": "", 
        "Nickname": "", 
        "Phone": "202-241-3252", 
        "Suffix": ""
    }, 
    "8D07": {
        "Address": "4020 1st Place SW; Washington, DC 20032", 
        "Email": "8D07@anc.dc.gov", 
        "First_Name": "Theresa", 
        "Last_Name": "Jones", 
        "Middle_Name": "H.", 
        "Nickname": "", 
        "Phone": "", 
        "Suffix": ""
    }, 
    "8E01": {
        "Address": "1425 Alabama Avenue SE; Washington, DC 20032", 
        "Email": "8E01@anc.dc.gov", 
        "First_Name": "Barbara", 
        "Last_Name": "Brown", 
        "Middle_Name": "A.", 
        "Nickname": "", 
        "Phone": "202-904-6565", 
        "Suffix": ""
    }, 
    "8E02": {
        "Address": "P.O. Box 73878; Washington, DC 20056", 
        "Email": "8E02@anc.dc.gov", 
        "First_Name": "Anthony", 
        "Last_Name": "Muhammad", 
        "Middle_Name": "", 
        "Nickname": "", 
        "Phone": "", 
        "Suffix": ""
    }, 
    "8E03": {
        "Address": "1920 Savannah Street SE; Washington, DC  20020", 
        "Email": "8E03@anc.dc.gov", 
        "First_Name": "Anthony", 
        "Last_Name": "Dailey", 
        "Middle_Name": "", 
        "Nickname": "", 
        "Phone": "", 
        "Suffix": ""
    }, 
    "8E04": {
        "Address": "1381Congress Street SE; Washington DC 20032", 
        "Email": "8E04@anc.dc.gov", 
        "First_Name": "Sharece", 
        "Last_Name": "Crawford", 
        "Middle_Name": "", 
        "Nickname": "", 
        "Phone": "", 
        "Suffix": ""
    }, 
    "8E05": {
        "Address": "1922 Valley Terrace SE; Washington, DC 20032", 
        "Email": "8E05@anc.dc.gov", 
        "First_Name": "Christopher", 
        "Last_Name": "Hawthorne", 
        "Middle_Name": "L.", 
        "Nickname": "", 
        "Phone": "", 
        "Suffix": ""
    }, 
    "8E06": {
        "Address": "559 Foxhall Place SE; Washington DC 20032", 
        "Email": "8E06@anc.dc.gov", 
        "First_Name": "Karlene", 
        "Last_Name": "Armstead", 
        "Middle_Name": "", 
        "Nickname": "(K.)", 
        "Phone": "", 
        "Suffix": ""
    }, 
    "8E07": {
        "Address": "847 Barnaby Street SE; Washington, DC 20032", 
        "Email": "8E07@anc.dc.gov", 
        "First_Name": "Sandra", 
        "Last_Name": "Williams", 
        "Middle_Name": "", 
        "Nickname": "(SV)", 
        "Phone": "", 
        "Suffix": ""
    }
}